["[\n  {\n    \"dateHourMinute\": \"202501190053\",\n    \"activeUsers\": 1,\n    \"parsed_year\": \"2025\",\n    \"parsed_month\": \"01\",\n    \"parsed_day\": \"19\",\n    \"parsed_hour\": \"00\",\n    \"parsed_minute\": \"53\",\n    \"parsed_year_month\": \"2025-01-01\",\n    \"parsed_year_month_day\": \"2025-01-19\",\n    \"parsed_year_month_day_hour\": \"2025-01-19 00:53:00\",\n    \"parsed_week\": 3,\n    \"parsed_wday\": 1,\n    \"parsed_wday_label\": \"Sunday\"\n  },\n  {\n    \"dateHourMinute\": \"202501190241\",\n    \"activeUsers\": 0,\n    \"parsed_year\": \"2025\",\n    \"parsed_month\": \"01\",\n    \"parsed_day\": \"19\",\n    \"parsed_hour\": \"02\",\n    \"parsed_minute\": \"41\",\n    \"parsed_year_month\": \"2025-01-01\",\n    \"parsed_year_month_day\": \"2025-01-19\",\n    \"parsed_year_month_day_hour\": \"2025-01-19 02:41:00\",\n    \"parsed_week\": 3,\n    \"parsed_wday\": 1,\n    \"parsed_wday_label\": \"Sunday\"\n  },\n  {\n    \"dateHourMinute\": \"202501191148\",\n    \"activeUsers\": 1,\n    \"parsed_year\": \"2025\",\n    \"parsed_month\": \"01\",\n    \"parsed_day\": \"19\",\n    \"parsed_hour\": \"11\",\n    \"parsed_minute\": \"48\",\n    \"parsed_year_month\": \"2025-01-01\",\n    \"parsed_year_month_day\": \"2025-01-19\",\n    \"parsed_year_month_day_hour\": \"2025-01-19 11:48:00\",\n    \"parsed_week\": 3,\n    \"parsed_wday\": 1,\n    \"parsed_wday_label\": \"Sunday\"\n  },\n  {\n    \"dateHourMinute\": \"202501191502\",\n    \"activeUsers\": 1,\n    \"parsed_year\": \"2025\",\n    \"parsed_month\": \"01\",\n    \"parsed_day\": \"19\",\n    \"parsed_hour\": \"15\",\n    \"parsed_minute\": \"02\",\n    \"parsed_year_month\": \"2025-01-01\",\n    \"parsed_year_month_day\": \"2025-01-19\",\n    \"parsed_year_month_day_hour\": \"2025-01-19 15:02:00\",\n    \"parsed_week\": 3,\n    \"parsed_wday\": 1,\n    \"parsed_wday_label\": \"Sunday\"\n  },\n  {\n    \"dateHourMinute\": \"202501191623\",\n    \"activeUsers\": 1,\n    \"parsed_year\": \"2025\",\n    \"parsed_month\": \"01\",\n    \"parsed_day\": \"19\",\n    \"parsed_hour\": \"16\",\n    \"parsed_minute\": \"23\",\n    \"parsed_year_month\": \"2025-01-01\",\n    \"parsed_year_month_day\": \"2025-01-19\",\n    \"parsed_year_month_day_hour\": \"2025-01-19 16:23:00\",\n    \"parsed_week\": 3,\n    \"parsed_wday\": 1,\n    \"parsed_wday_label\": \"Sunday\"\n  },\n  {\n    \"dateHourMinute\": \"202501191629\",\n    \"activeUsers\": 1,\n    \"parsed_year\": \"2025\",\n    \"parsed_month\": \"01\",\n    \"parsed_day\": \"19\",\n    \"parsed_hour\": \"16\",\n    \"parsed_minute\": \"29\",\n    \"parsed_year_month\": \"2025-01-01\",\n    \"parsed_year_month_day\": \"2025-01-19\",\n    \"parsed_year_month_day_hour\": \"2025-01-19 16:29:00\",\n    \"parsed_week\": 3,\n    \"parsed_wday\": 1,\n    \"parsed_wday_label\": \"Sunday\"\n  },\n  {\n    \"dateHourMinute\": \"202501191630\",\n    \"activeUsers\": 1,\n    \"parsed_year\": \"2025\",\n    \"parsed_month\": \"01\",\n    \"parsed_day\": \"19\",\n    \"parsed_hour\": \"16\",\n    \"parsed_minute\": \"30\",\n    \"parsed_year_month\": \"2025-01-01\",\n    \"parsed_year_month_day\": \"2025-01-19\",\n    \"parsed_year_month_day_hour\": \"2025-01-19 16:30:00\",\n    \"parsed_week\": 3,\n    \"parsed_wday\": 1,\n    \"parsed_wday_label\": \"Sunday\"\n  },\n  {\n    \"dateHourMinute\": \"202501191715\",\n    \"activeUsers\": 1,\n    \"parsed_year\": \"2025\",\n    \"parsed_month\": \"01\",\n    \"parsed_day\": \"19\",\n    \"parsed_hour\": \"17\",\n    \"parsed_minute\": \"15\",\n    \"parsed_year_month\": \"2025-01-01\",\n    \"parsed_year_month_day\": \"2025-01-19\",\n    \"parsed_year_month_day_hour\": \"2025-01-19 17:15:00\",\n    \"parsed_week\": 3,\n    \"parsed_wday\": 1,\n    \"parsed_wday_label\": \"Sunday\"\n  },\n  {\n    \"dateHourMinute\": \"202501192220\",\n    \"activeUsers\": 0,\n    \"parsed_year\": \"2025\",\n    \"parsed_month\": \"01\",\n    \"parsed_day\": \"19\",\n    \"parsed_hour\": \"22\",\n    \"parsed_minute\": \"20\",\n    \"parsed_year_month\": \"2025-01-01\",\n    \"parsed_year_month_day\": \"2025-01-19\",\n    \"parsed_year_month_day_hour\": \"2025-01-19 22:20:00\",\n    \"parsed_week\": 3,\n    \"parsed_wday\": 1,\n    \"parsed_wday_label\": \"Sunday\"\n  },\n  {\n    \"dateHourMinute\": \"202501192334\",\n    \"activeUsers\": 1,\n    \"parsed_year\": \"2025\",\n    \"parsed_month\": \"01\",\n    \"parsed_day\": \"19\",\n    \"parsed_hour\": \"23\",\n    \"parsed_minute\": \"34\",\n    \"parsed_year_month\": \"2025-01-01\",\n    \"parsed_year_month_day\": \"2025-01-19\",\n    \"parsed_year_month_day_hour\": \"2025-01-19 23:34:00\",\n    \"parsed_week\": 3,\n    \"parsed_wday\": 1,\n    \"parsed_wday_label\": \"Sunday\"\n  }\n]"]
