["[\n  {\n    \"dateHourMinute\": \"202405150019\",\n    \"activeUsers\": 1,\n    \"parsed_year\": \"2024\",\n    \"parsed_month\": \"05\",\n    \"parsed_day\": \"15\",\n    \"parsed_hour\": \"00\",\n    \"parsed_minute\": \"19\",\n    \"parsed_year_month\": \"2024-05-01\",\n    \"parsed_year_month_day\": \"2024-05-15\",\n    \"parsed_year_month_day_hour\": \"2024-05-15 00:19:00\",\n    \"parsed_week\": 20,\n    \"parsed_wday\": 4,\n    \"parsed_wday_label\": \"Wednesday\"\n  },\n  {\n    \"dateHourMinute\": \"202405150024\",\n    \"activeUsers\": 1,\n    \"parsed_year\": \"2024\",\n    \"parsed_month\": \"05\",\n    \"parsed_day\": \"15\",\n    \"parsed_hour\": \"00\",\n    \"parsed_minute\": \"24\",\n    \"parsed_year_month\": \"2024-05-01\",\n    \"parsed_year_month_day\": \"2024-05-15\",\n    \"parsed_year_month_day_hour\": \"2024-05-15 00:24:00\",\n    \"parsed_week\": 20,\n    \"parsed_wday\": 4,\n    \"parsed_wday_label\": \"Wednesday\"\n  },\n  {\n    \"dateHourMinute\": \"202405150102\",\n    \"activeUsers\": 1,\n    \"parsed_year\": \"2024\",\n    \"parsed_month\": \"05\",\n    \"parsed_day\": \"15\",\n    \"parsed_hour\": \"01\",\n    \"parsed_minute\": \"02\",\n    \"parsed_year_month\": \"2024-05-01\",\n    \"parsed_year_month_day\": \"2024-05-15\",\n    \"parsed_year_month_day_hour\": \"2024-05-15 01:02:00\",\n    \"parsed_week\": 20,\n    \"parsed_wday\": 4,\n    \"parsed_wday_label\": \"Wednesday\"\n  },\n  {\n    \"dateHourMinute\": \"202405150121\",\n    \"activeUsers\": 1,\n    \"parsed_year\": \"2024\",\n    \"parsed_month\": \"05\",\n    \"parsed_day\": \"15\",\n    \"parsed_hour\": \"01\",\n    \"parsed_minute\": \"21\",\n    \"parsed_year_month\": \"2024-05-01\",\n    \"parsed_year_month_day\": \"2024-05-15\",\n    \"parsed_year_month_day_hour\": \"2024-05-15 01:21:00\",\n    \"parsed_week\": 20,\n    \"parsed_wday\": 4,\n    \"parsed_wday_label\": \"Wednesday\"\n  },\n  {\n    \"dateHourMinute\": \"202405151040\",\n    \"activeUsers\": 1,\n    \"parsed_year\": \"2024\",\n    \"parsed_month\": \"05\",\n    \"parsed_day\": \"15\",\n    \"parsed_hour\": \"10\",\n    \"parsed_minute\": \"40\",\n    \"parsed_year_month\": \"2024-05-01\",\n    \"parsed_year_month_day\": \"2024-05-15\",\n    \"parsed_year_month_day_hour\": \"2024-05-15 10:40:00\",\n    \"parsed_week\": 20,\n    \"parsed_wday\": 4,\n    \"parsed_wday_label\": \"Wednesday\"\n  },\n  {\n    \"dateHourMinute\": \"202405151124\",\n    \"activeUsers\": 1,\n    \"parsed_year\": \"2024\",\n    \"parsed_month\": \"05\",\n    \"parsed_day\": \"15\",\n    \"parsed_hour\": \"11\",\n    \"parsed_minute\": \"24\",\n    \"parsed_year_month\": \"2024-05-01\",\n    \"parsed_year_month_day\": \"2024-05-15\",\n    \"parsed_year_month_day_hour\": \"2024-05-15 11:24:00\",\n    \"parsed_week\": 20,\n    \"parsed_wday\": 4,\n    \"parsed_wday_label\": \"Wednesday\"\n  },\n  {\n    \"dateHourMinute\": \"202405151533\",\n    \"activeUsers\": 1,\n    \"parsed_year\": \"2024\",\n    \"parsed_month\": \"05\",\n    \"parsed_day\": \"15\",\n    \"parsed_hour\": \"15\",\n    \"parsed_minute\": \"33\",\n    \"parsed_year_month\": \"2024-05-01\",\n    \"parsed_year_month_day\": \"2024-05-15\",\n    \"parsed_year_month_day_hour\": \"2024-05-15 15:33:00\",\n    \"parsed_week\": 20,\n    \"parsed_wday\": 4,\n    \"parsed_wday_label\": \"Wednesday\"\n  },\n  {\n    \"dateHourMinute\": \"202405151538\",\n    \"activeUsers\": 1,\n    \"parsed_year\": \"2024\",\n    \"parsed_month\": \"05\",\n    \"parsed_day\": \"15\",\n    \"parsed_hour\": \"15\",\n    \"parsed_minute\": \"38\",\n    \"parsed_year_month\": \"2024-05-01\",\n    \"parsed_year_month_day\": \"2024-05-15\",\n    \"parsed_year_month_day_hour\": \"2024-05-15 15:38:00\",\n    \"parsed_week\": 20,\n    \"parsed_wday\": 4,\n    \"parsed_wday_label\": \"Wednesday\"\n  },\n  {\n    \"dateHourMinute\": \"202405151539\",\n    \"activeUsers\": 1,\n    \"parsed_year\": \"2024\",\n    \"parsed_month\": \"05\",\n    \"parsed_day\": \"15\",\n    \"parsed_hour\": \"15\",\n    \"parsed_minute\": \"39\",\n    \"parsed_year_month\": \"2024-05-01\",\n    \"parsed_year_month_day\": \"2024-05-15\",\n    \"parsed_year_month_day_hour\": \"2024-05-15 15:39:00\",\n    \"parsed_week\": 20,\n    \"parsed_wday\": 4,\n    \"parsed_wday_label\": \"Wednesday\"\n  },\n  {\n    \"dateHourMinute\": \"202405151950\",\n    \"activeUsers\": 0,\n    \"parsed_year\": \"2024\",\n    \"parsed_month\": \"05\",\n    \"parsed_day\": \"15\",\n    \"parsed_hour\": \"19\",\n    \"parsed_minute\": \"50\",\n    \"parsed_year_month\": \"2024-05-01\",\n    \"parsed_year_month_day\": \"2024-05-15\",\n    \"parsed_year_month_day_hour\": \"2024-05-15 19:50:00\",\n    \"parsed_week\": 20,\n    \"parsed_wday\": 4,\n    \"parsed_wday_label\": \"Wednesday\"\n  },\n  {\n    \"dateHourMinute\": \"202405152013\",\n    \"activeUsers\": 1,\n    \"parsed_year\": \"2024\",\n    \"parsed_month\": \"05\",\n    \"parsed_day\": \"15\",\n    \"parsed_hour\": \"20\",\n    \"parsed_minute\": \"13\",\n    \"parsed_year_month\": \"2024-05-01\",\n    \"parsed_year_month_day\": \"2024-05-15\",\n    \"parsed_year_month_day_hour\": \"2024-05-15 20:13:00\",\n    \"parsed_week\": 20,\n    \"parsed_wday\": 4,\n    \"parsed_wday_label\": \"Wednesday\"\n  },\n  {\n    \"dateHourMinute\": \"202405152015\",\n    \"activeUsers\": 1,\n    \"parsed_year\": \"2024\",\n    \"parsed_month\": \"05\",\n    \"parsed_day\": \"15\",\n    \"parsed_hour\": \"20\",\n    \"parsed_minute\": \"15\",\n    \"parsed_year_month\": \"2024-05-01\",\n    \"parsed_year_month_day\": \"2024-05-15\",\n    \"parsed_year_month_day_hour\": \"2024-05-15 20:15:00\",\n    \"parsed_week\": 20,\n    \"parsed_wday\": 4,\n    \"parsed_wday_label\": \"Wednesday\"\n  },\n  {\n    \"dateHourMinute\": \"202405152131\",\n    \"activeUsers\": 0,\n    \"parsed_year\": \"2024\",\n    \"parsed_month\": \"05\",\n    \"parsed_day\": \"15\",\n    \"parsed_hour\": \"21\",\n    \"parsed_minute\": \"31\",\n    \"parsed_year_month\": \"2024-05-01\",\n    \"parsed_year_month_day\": \"2024-05-15\",\n    \"parsed_year_month_day_hour\": \"2024-05-15 21:31:00\",\n    \"parsed_week\": 20,\n    \"parsed_wday\": 4,\n    \"parsed_wday_label\": \"Wednesday\"\n  },\n  {\n    \"dateHourMinute\": \"202405152146\",\n    \"activeUsers\": 0,\n    \"parsed_year\": \"2024\",\n    \"parsed_month\": \"05\",\n    \"parsed_day\": \"15\",\n    \"parsed_hour\": \"21\",\n    \"parsed_minute\": \"46\",\n    \"parsed_year_month\": \"2024-05-01\",\n    \"parsed_year_month_day\": \"2024-05-15\",\n    \"parsed_year_month_day_hour\": \"2024-05-15 21:46:00\",\n    \"parsed_week\": 20,\n    \"parsed_wday\": 4,\n    \"parsed_wday_label\": \"Wednesday\"\n  },\n  {\n    \"dateHourMinute\": \"202405152213\",\n    \"activeUsers\": 1,\n    \"parsed_year\": \"2024\",\n    \"parsed_month\": \"05\",\n    \"parsed_day\": \"15\",\n    \"parsed_hour\": \"22\",\n    \"parsed_minute\": \"13\",\n    \"parsed_year_month\": \"2024-05-01\",\n    \"parsed_year_month_day\": \"2024-05-15\",\n    \"parsed_year_month_day_hour\": \"2024-05-15 22:13:00\",\n    \"parsed_week\": 20,\n    \"parsed_wday\": 4,\n    \"parsed_wday_label\": \"Wednesday\"\n  },\n  {\n    \"dateHourMinute\": \"202405152214\",\n    \"activeUsers\": 1,\n    \"parsed_year\": \"2024\",\n    \"parsed_month\": \"05\",\n    \"parsed_day\": \"15\",\n    \"parsed_hour\": \"22\",\n    \"parsed_minute\": \"14\",\n    \"parsed_year_month\": \"2024-05-01\",\n    \"parsed_year_month_day\": \"2024-05-15\",\n    \"parsed_year_month_day_hour\": \"2024-05-15 22:14:00\",\n    \"parsed_week\": 20,\n    \"parsed_wday\": 4,\n    \"parsed_wday_label\": \"Wednesday\"\n  },\n  {\n    \"dateHourMinute\": \"202405152249\",\n    \"activeUsers\": 1,\n    \"parsed_year\": \"2024\",\n    \"parsed_month\": \"05\",\n    \"parsed_day\": \"15\",\n    \"parsed_hour\": \"22\",\n    \"parsed_minute\": \"49\",\n    \"parsed_year_month\": \"2024-05-01\",\n    \"parsed_year_month_day\": \"2024-05-15\",\n    \"parsed_year_month_day_hour\": \"2024-05-15 22:49:00\",\n    \"parsed_week\": 20,\n    \"parsed_wday\": 4,\n    \"parsed_wday_label\": \"Wednesday\"\n  },\n  {\n    \"dateHourMinute\": \"202405152255\",\n    \"activeUsers\": 1,\n    \"parsed_year\": \"2024\",\n    \"parsed_month\": \"05\",\n    \"parsed_day\": \"15\",\n    \"parsed_hour\": \"22\",\n    \"parsed_minute\": \"55\",\n    \"parsed_year_month\": \"2024-05-01\",\n    \"parsed_year_month_day\": \"2024-05-15\",\n    \"parsed_year_month_day_hour\": \"2024-05-15 22:55:00\",\n    \"parsed_week\": 20,\n    \"parsed_wday\": 4,\n    \"parsed_wday_label\": \"Wednesday\"\n  },\n  {\n    \"dateHourMinute\": \"202405152331\",\n    \"activeUsers\": 1,\n    \"parsed_year\": \"2024\",\n    \"parsed_month\": \"05\",\n    \"parsed_day\": \"15\",\n    \"parsed_hour\": \"23\",\n    \"parsed_minute\": \"31\",\n    \"parsed_year_month\": \"2024-05-01\",\n    \"parsed_year_month_day\": \"2024-05-15\",\n    \"parsed_year_month_day_hour\": \"2024-05-15 23:31:00\",\n    \"parsed_week\": 20,\n    \"parsed_wday\": 4,\n    \"parsed_wday_label\": \"Wednesday\"\n  }\n]"]
