["[\n  {\n    \"dateHourMinute\": \"202602280244\",\n    \"activeUsers\": 1,\n    \"parsed_year\": \"2026\",\n    \"parsed_month\": \"02\",\n    \"parsed_day\": \"28\",\n    \"parsed_hour\": \"02\",\n    \"parsed_minute\": \"44\",\n    \"parsed_year_month\": \"2026-02-01\",\n    \"parsed_year_month_day\": \"2026-02-28\",\n    \"parsed_year_month_day_hour\": \"2026-02-28 02:44:00\",\n    \"parsed_week\": 9,\n    \"parsed_wday\": 7,\n    \"parsed_wday_label\": \"Saturday\"\n  },\n  {\n    \"dateHourMinute\": \"202602281351\",\n    \"activeUsers\": 1,\n    \"parsed_year\": \"2026\",\n    \"parsed_month\": \"02\",\n    \"parsed_day\": \"28\",\n    \"parsed_hour\": \"13\",\n    \"parsed_minute\": \"51\",\n    \"parsed_year_month\": \"2026-02-01\",\n    \"parsed_year_month_day\": \"2026-02-28\",\n    \"parsed_year_month_day_hour\": \"2026-02-28 13:51:00\",\n    \"parsed_week\": 9,\n    \"parsed_wday\": 7,\n    \"parsed_wday_label\": \"Saturday\"\n  },\n  {\n    \"dateHourMinute\": \"202602281613\",\n    \"activeUsers\": 1,\n    \"parsed_year\": \"2026\",\n    \"parsed_month\": \"02\",\n    \"parsed_day\": \"28\",\n    \"parsed_hour\": \"16\",\n    \"parsed_minute\": \"13\",\n    \"parsed_year_month\": \"2026-02-01\",\n    \"parsed_year_month_day\": \"2026-02-28\",\n    \"parsed_year_month_day_hour\": \"2026-02-28 16:13:00\",\n    \"parsed_week\": 9,\n    \"parsed_wday\": 7,\n    \"parsed_wday_label\": \"Saturday\"\n  },\n  {\n    \"dateHourMinute\": \"202602281742\",\n    \"activeUsers\": 1,\n    \"parsed_year\": \"2026\",\n    \"parsed_month\": \"02\",\n    \"parsed_day\": \"28\",\n    \"parsed_hour\": \"17\",\n    \"parsed_minute\": \"42\",\n    \"parsed_year_month\": \"2026-02-01\",\n    \"parsed_year_month_day\": \"2026-02-28\",\n    \"parsed_year_month_day_hour\": \"2026-02-28 17:42:00\",\n    \"parsed_week\": 9,\n    \"parsed_wday\": 7,\n    \"parsed_wday_label\": \"Saturday\"\n  },\n  {\n    \"dateHourMinute\": \"202602281756\",\n    \"activeUsers\": 1,\n    \"parsed_year\": \"2026\",\n    \"parsed_month\": \"02\",\n    \"parsed_day\": \"28\",\n    \"parsed_hour\": \"17\",\n    \"parsed_minute\": \"56\",\n    \"parsed_year_month\": \"2026-02-01\",\n    \"parsed_year_month_day\": \"2026-02-28\",\n    \"parsed_year_month_day_hour\": \"2026-02-28 17:56:00\",\n    \"parsed_week\": 9,\n    \"parsed_wday\": 7,\n    \"parsed_wday_label\": \"Saturday\"\n  },\n  {\n    \"dateHourMinute\": \"202602282042\",\n    \"activeUsers\": 1,\n    \"parsed_year\": \"2026\",\n    \"parsed_month\": \"02\",\n    \"parsed_day\": \"28\",\n    \"parsed_hour\": \"20\",\n    \"parsed_minute\": \"42\",\n    \"parsed_year_month\": \"2026-02-01\",\n    \"parsed_year_month_day\": \"2026-02-28\",\n    \"parsed_year_month_day_hour\": \"2026-02-28 20:42:00\",\n    \"parsed_week\": 9,\n    \"parsed_wday\": 7,\n    \"parsed_wday_label\": \"Saturday\"\n  },\n  {\n    \"dateHourMinute\": \"202602282123\",\n    \"activeUsers\": 1,\n    \"parsed_year\": \"2026\",\n    \"parsed_month\": \"02\",\n    \"parsed_day\": \"28\",\n    \"parsed_hour\": \"21\",\n    \"parsed_minute\": \"23\",\n    \"parsed_year_month\": \"2026-02-01\",\n    \"parsed_year_month_day\": \"2026-02-28\",\n    \"parsed_year_month_day_hour\": \"2026-02-28 21:23:00\",\n    \"parsed_week\": 9,\n    \"parsed_wday\": 7,\n    \"parsed_wday_label\": \"Saturday\"\n  },\n  {\n    \"dateHourMinute\": \"202602282152\",\n    \"activeUsers\": 1,\n    \"parsed_year\": \"2026\",\n    \"parsed_month\": \"02\",\n    \"parsed_day\": \"28\",\n    \"parsed_hour\": \"21\",\n    \"parsed_minute\": \"52\",\n    \"parsed_year_month\": \"2026-02-01\",\n    \"parsed_year_month_day\": \"2026-02-28\",\n    \"parsed_year_month_day_hour\": \"2026-02-28 21:52:00\",\n    \"parsed_week\": 9,\n    \"parsed_wday\": 7,\n    \"parsed_wday_label\": \"Saturday\"\n  },\n  {\n    \"dateHourMinute\": \"202602282218\",\n    \"activeUsers\": 1,\n    \"parsed_year\": \"2026\",\n    \"parsed_month\": \"02\",\n    \"parsed_day\": \"28\",\n    \"parsed_hour\": \"22\",\n    \"parsed_minute\": \"18\",\n    \"parsed_year_month\": \"2026-02-01\",\n    \"parsed_year_month_day\": \"2026-02-28\",\n    \"parsed_year_month_day_hour\": \"2026-02-28 22:18:00\",\n    \"parsed_week\": 9,\n    \"parsed_wday\": 7,\n    \"parsed_wday_label\": \"Saturday\"\n  }\n]"]