["[\n  {\n    \"dateHourMinute\": \"202503090222\",\n    \"activeUsers\": 1,\n    \"parsed_year\": \"2025\",\n    \"parsed_month\": \"03\",\n    \"parsed_day\": \"09\",\n    \"parsed_hour\": \"02\",\n    \"parsed_minute\": \"22\",\n    \"parsed_year_month\": \"2025-03-01\",\n    \"parsed_year_month_day\": \"2025-03-09\",\n    \"parsed_year_month_day_hour\": \"2025-03-09 02:22:00\",\n    \"parsed_week\": 10,\n    \"parsed_wday\": 1,\n    \"parsed_wday_label\": \"Sunday\"\n  },\n  {\n    \"dateHourMinute\": \"202503090617\",\n    \"activeUsers\": 1,\n    \"parsed_year\": \"2025\",\n    \"parsed_month\": \"03\",\n    \"parsed_day\": \"09\",\n    \"parsed_hour\": \"06\",\n    \"parsed_minute\": \"17\",\n    \"parsed_year_month\": \"2025-03-01\",\n    \"parsed_year_month_day\": \"2025-03-09\",\n    \"parsed_year_month_day_hour\": \"2025-03-09 06:17:00\",\n    \"parsed_week\": 10,\n    \"parsed_wday\": 1,\n    \"parsed_wday_label\": \"Sunday\"\n  },\n  {\n    \"dateHourMinute\": \"202503090618\",\n    \"activeUsers\": 1,\n    \"parsed_year\": \"2025\",\n    \"parsed_month\": \"03\",\n    \"parsed_day\": \"09\",\n    \"parsed_hour\": \"06\",\n    \"parsed_minute\": \"18\",\n    \"parsed_year_month\": \"2025-03-01\",\n    \"parsed_year_month_day\": \"2025-03-09\",\n    \"parsed_year_month_day_hour\": \"2025-03-09 06:18:00\",\n    \"parsed_week\": 10,\n    \"parsed_wday\": 1,\n    \"parsed_wday_label\": \"Sunday\"\n  },\n  {\n    \"dateHourMinute\": \"202503091349\",\n    \"activeUsers\": 1,\n    \"parsed_year\": \"2025\",\n    \"parsed_month\": \"03\",\n    \"parsed_day\": \"09\",\n    \"parsed_hour\": \"13\",\n    \"parsed_minute\": \"49\",\n    \"parsed_year_month\": \"2025-03-01\",\n    \"parsed_year_month_day\": \"2025-03-09\",\n    \"parsed_year_month_day_hour\": \"2025-03-09 13:49:00\",\n    \"parsed_week\": 10,\n    \"parsed_wday\": 1,\n    \"parsed_wday_label\": \"Sunday\"\n  },\n  {\n    \"dateHourMinute\": \"202503091350\",\n    \"activeUsers\": 1,\n    \"parsed_year\": \"2025\",\n    \"parsed_month\": \"03\",\n    \"parsed_day\": \"09\",\n    \"parsed_hour\": \"13\",\n    \"parsed_minute\": \"50\",\n    \"parsed_year_month\": \"2025-03-01\",\n    \"parsed_year_month_day\": \"2025-03-09\",\n    \"parsed_year_month_day_hour\": \"2025-03-09 13:50:00\",\n    \"parsed_week\": 10,\n    \"parsed_wday\": 1,\n    \"parsed_wday_label\": \"Sunday\"\n  },\n  {\n    \"dateHourMinute\": \"202503092220\",\n    \"activeUsers\": 1,\n    \"parsed_year\": \"2025\",\n    \"parsed_month\": \"03\",\n    \"parsed_day\": \"09\",\n    \"parsed_hour\": \"22\",\n    \"parsed_minute\": \"20\",\n    \"parsed_year_month\": \"2025-03-01\",\n    \"parsed_year_month_day\": \"2025-03-09\",\n    \"parsed_year_month_day_hour\": \"2025-03-09 22:20:00\",\n    \"parsed_week\": 10,\n    \"parsed_wday\": 1,\n    \"parsed_wday_label\": \"Sunday\"\n  }\n]"]
