["[\n  {\n    \"dateHourMinute\": \"202409060701\",\n    \"activeUsers\": 1,\n    \"parsed_year\": \"2024\",\n    \"parsed_month\": \"09\",\n    \"parsed_day\": \"06\",\n    \"parsed_hour\": \"07\",\n    \"parsed_minute\": \"01\",\n    \"parsed_year_month\": \"2024-09-01\",\n    \"parsed_year_month_day\": \"2024-09-06\",\n    \"parsed_year_month_day_hour\": \"2024-09-06 07:01:00\",\n    \"parsed_week\": 36,\n    \"parsed_wday\": 6,\n    \"parsed_wday_label\": \"Friday\"\n  },\n  {\n    \"dateHourMinute\": \"202409060703\",\n    \"activeUsers\": 1,\n    \"parsed_year\": \"2024\",\n    \"parsed_month\": \"09\",\n    \"parsed_day\": \"06\",\n    \"parsed_hour\": \"07\",\n    \"parsed_minute\": \"03\",\n    \"parsed_year_month\": \"2024-09-01\",\n    \"parsed_year_month_day\": \"2024-09-06\",\n    \"parsed_year_month_day_hour\": \"2024-09-06 07:03:00\",\n    \"parsed_week\": 36,\n    \"parsed_wday\": 6,\n    \"parsed_wday_label\": \"Friday\"\n  },\n  {\n    \"dateHourMinute\": \"202409060940\",\n    \"activeUsers\": 1,\n    \"parsed_year\": \"2024\",\n    \"parsed_month\": \"09\",\n    \"parsed_day\": \"06\",\n    \"parsed_hour\": \"09\",\n    \"parsed_minute\": \"40\",\n    \"parsed_year_month\": \"2024-09-01\",\n    \"parsed_year_month_day\": \"2024-09-06\",\n    \"parsed_year_month_day_hour\": \"2024-09-06 09:40:00\",\n    \"parsed_week\": 36,\n    \"parsed_wday\": 6,\n    \"parsed_wday_label\": \"Friday\"\n  },\n  {\n    \"dateHourMinute\": \"202409060942\",\n    \"activeUsers\": 1,\n    \"parsed_year\": \"2024\",\n    \"parsed_month\": \"09\",\n    \"parsed_day\": \"06\",\n    \"parsed_hour\": \"09\",\n    \"parsed_minute\": \"42\",\n    \"parsed_year_month\": \"2024-09-01\",\n    \"parsed_year_month_day\": \"2024-09-06\",\n    \"parsed_year_month_day_hour\": \"2024-09-06 09:42:00\",\n    \"parsed_week\": 36,\n    \"parsed_wday\": 6,\n    \"parsed_wday_label\": \"Friday\"\n  },\n  {\n    \"dateHourMinute\": \"202409061119\",\n    \"activeUsers\": 0,\n    \"parsed_year\": \"2024\",\n    \"parsed_month\": \"09\",\n    \"parsed_day\": \"06\",\n    \"parsed_hour\": \"11\",\n    \"parsed_minute\": \"19\",\n    \"parsed_year_month\": \"2024-09-01\",\n    \"parsed_year_month_day\": \"2024-09-06\",\n    \"parsed_year_month_day_hour\": \"2024-09-06 11:19:00\",\n    \"parsed_week\": 36,\n    \"parsed_wday\": 6,\n    \"parsed_wday_label\": \"Friday\"\n  },\n  {\n    \"dateHourMinute\": \"202409061125\",\n    \"activeUsers\": 1,\n    \"parsed_year\": \"2024\",\n    \"parsed_month\": \"09\",\n    \"parsed_day\": \"06\",\n    \"parsed_hour\": \"11\",\n    \"parsed_minute\": \"25\",\n    \"parsed_year_month\": \"2024-09-01\",\n    \"parsed_year_month_day\": \"2024-09-06\",\n    \"parsed_year_month_day_hour\": \"2024-09-06 11:25:00\",\n    \"parsed_week\": 36,\n    \"parsed_wday\": 6,\n    \"parsed_wday_label\": \"Friday\"\n  },\n  {\n    \"dateHourMinute\": \"202409061200\",\n    \"activeUsers\": 1,\n    \"parsed_year\": \"2024\",\n    \"parsed_month\": \"09\",\n    \"parsed_day\": \"06\",\n    \"parsed_hour\": \"12\",\n    \"parsed_minute\": \"00\",\n    \"parsed_year_month\": \"2024-09-01\",\n    \"parsed_year_month_day\": \"2024-09-06\",\n    \"parsed_year_month_day_hour\": \"2024-09-06 12:00:00\",\n    \"parsed_week\": 36,\n    \"parsed_wday\": 6,\n    \"parsed_wday_label\": \"Friday\"\n  },\n  {\n    \"dateHourMinute\": \"202409061308\",\n    \"activeUsers\": 1,\n    \"parsed_year\": \"2024\",\n    \"parsed_month\": \"09\",\n    \"parsed_day\": \"06\",\n    \"parsed_hour\": \"13\",\n    \"parsed_minute\": \"08\",\n    \"parsed_year_month\": \"2024-09-01\",\n    \"parsed_year_month_day\": \"2024-09-06\",\n    \"parsed_year_month_day_hour\": \"2024-09-06 13:08:00\",\n    \"parsed_week\": 36,\n    \"parsed_wday\": 6,\n    \"parsed_wday_label\": \"Friday\"\n  },\n  {\n    \"dateHourMinute\": \"202409061321\",\n    \"activeUsers\": 1,\n    \"parsed_year\": \"2024\",\n    \"parsed_month\": \"09\",\n    \"parsed_day\": \"06\",\n    \"parsed_hour\": \"13\",\n    \"parsed_minute\": \"21\",\n    \"parsed_year_month\": \"2024-09-01\",\n    \"parsed_year_month_day\": \"2024-09-06\",\n    \"parsed_year_month_day_hour\": \"2024-09-06 13:21:00\",\n    \"parsed_week\": 36,\n    \"parsed_wday\": 6,\n    \"parsed_wday_label\": \"Friday\"\n  },\n  {\n    \"dateHourMinute\": \"202409061325\",\n    \"activeUsers\": 1,\n    \"parsed_year\": \"2024\",\n    \"parsed_month\": \"09\",\n    \"parsed_day\": \"06\",\n    \"parsed_hour\": \"13\",\n    \"parsed_minute\": \"25\",\n    \"parsed_year_month\": \"2024-09-01\",\n    \"parsed_year_month_day\": \"2024-09-06\",\n    \"parsed_year_month_day_hour\": \"2024-09-06 13:25:00\",\n    \"parsed_week\": 36,\n    \"parsed_wday\": 6,\n    \"parsed_wday_label\": \"Friday\"\n  },\n  {\n    \"dateHourMinute\": \"202409061353\",\n    \"activeUsers\": 1,\n    \"parsed_year\": \"2024\",\n    \"parsed_month\": \"09\",\n    \"parsed_day\": \"06\",\n    \"parsed_hour\": \"13\",\n    \"parsed_minute\": \"53\",\n    \"parsed_year_month\": \"2024-09-01\",\n    \"parsed_year_month_day\": \"2024-09-06\",\n    \"parsed_year_month_day_hour\": \"2024-09-06 13:53:00\",\n    \"parsed_week\": 36,\n    \"parsed_wday\": 6,\n    \"parsed_wday_label\": \"Friday\"\n  },\n  {\n    \"dateHourMinute\": \"202409061441\",\n    \"activeUsers\": 1,\n    \"parsed_year\": \"2024\",\n    \"parsed_month\": \"09\",\n    \"parsed_day\": \"06\",\n    \"parsed_hour\": \"14\",\n    \"parsed_minute\": \"41\",\n    \"parsed_year_month\": \"2024-09-01\",\n    \"parsed_year_month_day\": \"2024-09-06\",\n    \"parsed_year_month_day_hour\": \"2024-09-06 14:41:00\",\n    \"parsed_week\": 36,\n    \"parsed_wday\": 6,\n    \"parsed_wday_label\": \"Friday\"\n  },\n  {\n    \"dateHourMinute\": \"202409061443\",\n    \"activeUsers\": 1,\n    \"parsed_year\": \"2024\",\n    \"parsed_month\": \"09\",\n    \"parsed_day\": \"06\",\n    \"parsed_hour\": \"14\",\n    \"parsed_minute\": \"43\",\n    \"parsed_year_month\": \"2024-09-01\",\n    \"parsed_year_month_day\": \"2024-09-06\",\n    \"parsed_year_month_day_hour\": \"2024-09-06 14:43:00\",\n    \"parsed_week\": 36,\n    \"parsed_wday\": 6,\n    \"parsed_wday_label\": \"Friday\"\n  },\n  {\n    \"dateHourMinute\": \"202409061444\",\n    \"activeUsers\": 1,\n    \"parsed_year\": \"2024\",\n    \"parsed_month\": \"09\",\n    \"parsed_day\": \"06\",\n    \"parsed_hour\": \"14\",\n    \"parsed_minute\": \"44\",\n    \"parsed_year_month\": \"2024-09-01\",\n    \"parsed_year_month_day\": \"2024-09-06\",\n    \"parsed_year_month_day_hour\": \"2024-09-06 14:44:00\",\n    \"parsed_week\": 36,\n    \"parsed_wday\": 6,\n    \"parsed_wday_label\": \"Friday\"\n  },\n  {\n    \"dateHourMinute\": \"202409061445\",\n    \"activeUsers\": 1,\n    \"parsed_year\": \"2024\",\n    \"parsed_month\": \"09\",\n    \"parsed_day\": \"06\",\n    \"parsed_hour\": \"14\",\n    \"parsed_minute\": \"45\",\n    \"parsed_year_month\": \"2024-09-01\",\n    \"parsed_year_month_day\": \"2024-09-06\",\n    \"parsed_year_month_day_hour\": \"2024-09-06 14:45:00\",\n    \"parsed_week\": 36,\n    \"parsed_wday\": 6,\n    \"parsed_wday_label\": \"Friday\"\n  },\n  {\n    \"dateHourMinute\": \"202409061512\",\n    \"activeUsers\": 1,\n    \"parsed_year\": \"2024\",\n    \"parsed_month\": \"09\",\n    \"parsed_day\": \"06\",\n    \"parsed_hour\": \"15\",\n    \"parsed_minute\": \"12\",\n    \"parsed_year_month\": \"2024-09-01\",\n    \"parsed_year_month_day\": \"2024-09-06\",\n    \"parsed_year_month_day_hour\": \"2024-09-06 15:12:00\",\n    \"parsed_week\": 36,\n    \"parsed_wday\": 6,\n    \"parsed_wday_label\": \"Friday\"\n  },\n  {\n    \"dateHourMinute\": \"202409061513\",\n    \"activeUsers\": 1,\n    \"parsed_year\": \"2024\",\n    \"parsed_month\": \"09\",\n    \"parsed_day\": \"06\",\n    \"parsed_hour\": \"15\",\n    \"parsed_minute\": \"13\",\n    \"parsed_year_month\": \"2024-09-01\",\n    \"parsed_year_month_day\": \"2024-09-06\",\n    \"parsed_year_month_day_hour\": \"2024-09-06 15:13:00\",\n    \"parsed_week\": 36,\n    \"parsed_wday\": 6,\n    \"parsed_wday_label\": \"Friday\"\n  },\n  {\n    \"dateHourMinute\": \"202409061631\",\n    \"activeUsers\": 1,\n    \"parsed_year\": \"2024\",\n    \"parsed_month\": \"09\",\n    \"parsed_day\": \"06\",\n    \"parsed_hour\": \"16\",\n    \"parsed_minute\": \"31\",\n    \"parsed_year_month\": \"2024-09-01\",\n    \"parsed_year_month_day\": \"2024-09-06\",\n    \"parsed_year_month_day_hour\": \"2024-09-06 16:31:00\",\n    \"parsed_week\": 36,\n    \"parsed_wday\": 6,\n    \"parsed_wday_label\": \"Friday\"\n  },\n  {\n    \"dateHourMinute\": \"202409061637\",\n    \"activeUsers\": 1,\n    \"parsed_year\": \"2024\",\n    \"parsed_month\": \"09\",\n    \"parsed_day\": \"06\",\n    \"parsed_hour\": \"16\",\n    \"parsed_minute\": \"37\",\n    \"parsed_year_month\": \"2024-09-01\",\n    \"parsed_year_month_day\": \"2024-09-06\",\n    \"parsed_year_month_day_hour\": \"2024-09-06 16:37:00\",\n    \"parsed_week\": 36,\n    \"parsed_wday\": 6,\n    \"parsed_wday_label\": \"Friday\"\n  },\n  {\n    \"dateHourMinute\": \"202409061640\",\n    \"activeUsers\": 0,\n    \"parsed_year\": \"2024\",\n    \"parsed_month\": \"09\",\n    \"parsed_day\": \"06\",\n    \"parsed_hour\": \"16\",\n    \"parsed_minute\": \"40\",\n    \"parsed_year_month\": \"2024-09-01\",\n    \"parsed_year_month_day\": \"2024-09-06\",\n    \"parsed_year_month_day_hour\": \"2024-09-06 16:40:00\",\n    \"parsed_week\": 36,\n    \"parsed_wday\": 6,\n    \"parsed_wday_label\": \"Friday\"\n  },\n  {\n    \"dateHourMinute\": \"202409061641\",\n    \"activeUsers\": 1,\n    \"parsed_year\": \"2024\",\n    \"parsed_month\": \"09\",\n    \"parsed_day\": \"06\",\n    \"parsed_hour\": \"16\",\n    \"parsed_minute\": \"41\",\n    \"parsed_year_month\": \"2024-09-01\",\n    \"parsed_year_month_day\": \"2024-09-06\",\n    \"parsed_year_month_day_hour\": \"2024-09-06 16:41:00\",\n    \"parsed_week\": 36,\n    \"parsed_wday\": 6,\n    \"parsed_wday_label\": \"Friday\"\n  },\n  {\n    \"dateHourMinute\": \"202409061750\",\n    \"activeUsers\": 1,\n    \"parsed_year\": \"2024\",\n    \"parsed_month\": \"09\",\n    \"parsed_day\": \"06\",\n    \"parsed_hour\": \"17\",\n    \"parsed_minute\": \"50\",\n    \"parsed_year_month\": \"2024-09-01\",\n    \"parsed_year_month_day\": \"2024-09-06\",\n    \"parsed_year_month_day_hour\": \"2024-09-06 17:50:00\",\n    \"parsed_week\": 36,\n    \"parsed_wday\": 6,\n    \"parsed_wday_label\": \"Friday\"\n  },\n  {\n    \"dateHourMinute\": \"202409061759\",\n    \"activeUsers\": 1,\n    \"parsed_year\": \"2024\",\n    \"parsed_month\": \"09\",\n    \"parsed_day\": \"06\",\n    \"parsed_hour\": \"17\",\n    \"parsed_minute\": \"59\",\n    \"parsed_year_month\": \"2024-09-01\",\n    \"parsed_year_month_day\": \"2024-09-06\",\n    \"parsed_year_month_day_hour\": \"2024-09-06 17:59:00\",\n    \"parsed_week\": 36,\n    \"parsed_wday\": 6,\n    \"parsed_wday_label\": \"Friday\"\n  },\n  {\n    \"dateHourMinute\": \"202409061917\",\n    \"activeUsers\": 1,\n    \"parsed_year\": \"2024\",\n    \"parsed_month\": \"09\",\n    \"parsed_day\": \"06\",\n    \"parsed_hour\": \"19\",\n    \"parsed_minute\": \"17\",\n    \"parsed_year_month\": \"2024-09-01\",\n    \"parsed_year_month_day\": \"2024-09-06\",\n    \"parsed_year_month_day_hour\": \"2024-09-06 19:17:00\",\n    \"parsed_week\": 36,\n    \"parsed_wday\": 6,\n    \"parsed_wday_label\": \"Friday\"\n  },\n  {\n    \"dateHourMinute\": \"202409062002\",\n    \"activeUsers\": 1,\n    \"parsed_year\": \"2024\",\n    \"parsed_month\": \"09\",\n    \"parsed_day\": \"06\",\n    \"parsed_hour\": \"20\",\n    \"parsed_minute\": \"02\",\n    \"parsed_year_month\": \"2024-09-01\",\n    \"parsed_year_month_day\": \"2024-09-06\",\n    \"parsed_year_month_day_hour\": \"2024-09-06 20:02:00\",\n    \"parsed_week\": 36,\n    \"parsed_wday\": 6,\n    \"parsed_wday_label\": \"Friday\"\n  },\n  {\n    \"dateHourMinute\": \"202409062003\",\n    \"activeUsers\": 1,\n    \"parsed_year\": \"2024\",\n    \"parsed_month\": \"09\",\n    \"parsed_day\": \"06\",\n    \"parsed_hour\": \"20\",\n    \"parsed_minute\": \"03\",\n    \"parsed_year_month\": \"2024-09-01\",\n    \"parsed_year_month_day\": \"2024-09-06\",\n    \"parsed_year_month_day_hour\": \"2024-09-06 20:03:00\",\n    \"parsed_week\": 36,\n    \"parsed_wday\": 6,\n    \"parsed_wday_label\": \"Friday\"\n  },\n  {\n    \"dateHourMinute\": \"202409062039\",\n    \"activeUsers\": 1,\n    \"parsed_year\": \"2024\",\n    \"parsed_month\": \"09\",\n    \"parsed_day\": \"06\",\n    \"parsed_hour\": \"20\",\n    \"parsed_minute\": \"39\",\n    \"parsed_year_month\": \"2024-09-01\",\n    \"parsed_year_month_day\": \"2024-09-06\",\n    \"parsed_year_month_day_hour\": \"2024-09-06 20:39:00\",\n    \"parsed_week\": 36,\n    \"parsed_wday\": 6,\n    \"parsed_wday_label\": \"Friday\"\n  },\n  {\n    \"dateHourMinute\": \"202409062044\",\n    \"activeUsers\": 1,\n    \"parsed_year\": \"2024\",\n    \"parsed_month\": \"09\",\n    \"parsed_day\": \"06\",\n    \"parsed_hour\": \"20\",\n    \"parsed_minute\": \"44\",\n    \"parsed_year_month\": \"2024-09-01\",\n    \"parsed_year_month_day\": \"2024-09-06\",\n    \"parsed_year_month_day_hour\": \"2024-09-06 20:44:00\",\n    \"parsed_week\": 36,\n    \"parsed_wday\": 6,\n    \"parsed_wday_label\": \"Friday\"\n  },\n  {\n    \"dateHourMinute\": \"202409062046\",\n    \"activeUsers\": 1,\n    \"parsed_year\": \"2024\",\n    \"parsed_month\": \"09\",\n    \"parsed_day\": \"06\",\n    \"parsed_hour\": \"20\",\n    \"parsed_minute\": \"46\",\n    \"parsed_year_month\": \"2024-09-01\",\n    \"parsed_year_month_day\": \"2024-09-06\",\n    \"parsed_year_month_day_hour\": \"2024-09-06 20:46:00\",\n    \"parsed_week\": 36,\n    \"parsed_wday\": 6,\n    \"parsed_wday_label\": \"Friday\"\n  }\n]"]
