["[\n  {\n    \"dateHourMinute\": \"202406030354\",\n    \"activeUsers\": 1,\n    \"parsed_year\": \"2024\",\n    \"parsed_month\": \"06\",\n    \"parsed_day\": \"03\",\n    \"parsed_hour\": \"03\",\n    \"parsed_minute\": \"54\",\n    \"parsed_year_month\": \"2024-06-01\",\n    \"parsed_year_month_day\": \"2024-06-03\",\n    \"parsed_year_month_day_hour\": \"2024-06-03 03:54:00\",\n    \"parsed_week\": 23,\n    \"parsed_wday\": 2,\n    \"parsed_wday_label\": \"Monday\"\n  },\n  {\n    \"dateHourMinute\": \"202406030355\",\n    \"activeUsers\": 0,\n    \"parsed_year\": \"2024\",\n    \"parsed_month\": \"06\",\n    \"parsed_day\": \"03\",\n    \"parsed_hour\": \"03\",\n    \"parsed_minute\": \"55\",\n    \"parsed_year_month\": \"2024-06-01\",\n    \"parsed_year_month_day\": \"2024-06-03\",\n    \"parsed_year_month_day_hour\": \"2024-06-03 03:55:00\",\n    \"parsed_week\": 23,\n    \"parsed_wday\": 2,\n    \"parsed_wday_label\": \"Monday\"\n  },\n  {\n    \"dateHourMinute\": \"202406030356\",\n    \"activeUsers\": 1,\n    \"parsed_year\": \"2024\",\n    \"parsed_month\": \"06\",\n    \"parsed_day\": \"03\",\n    \"parsed_hour\": \"03\",\n    \"parsed_minute\": \"56\",\n    \"parsed_year_month\": \"2024-06-01\",\n    \"parsed_year_month_day\": \"2024-06-03\",\n    \"parsed_year_month_day_hour\": \"2024-06-03 03:56:00\",\n    \"parsed_week\": 23,\n    \"parsed_wday\": 2,\n    \"parsed_wday_label\": \"Monday\"\n  },\n  {\n    \"dateHourMinute\": \"202406030413\",\n    \"activeUsers\": 1,\n    \"parsed_year\": \"2024\",\n    \"parsed_month\": \"06\",\n    \"parsed_day\": \"03\",\n    \"parsed_hour\": \"04\",\n    \"parsed_minute\": \"13\",\n    \"parsed_year_month\": \"2024-06-01\",\n    \"parsed_year_month_day\": \"2024-06-03\",\n    \"parsed_year_month_day_hour\": \"2024-06-03 04:13:00\",\n    \"parsed_week\": 23,\n    \"parsed_wday\": 2,\n    \"parsed_wday_label\": \"Monday\"\n  },\n  {\n    \"dateHourMinute\": \"202406030438\",\n    \"activeUsers\": 1,\n    \"parsed_year\": \"2024\",\n    \"parsed_month\": \"06\",\n    \"parsed_day\": \"03\",\n    \"parsed_hour\": \"04\",\n    \"parsed_minute\": \"38\",\n    \"parsed_year_month\": \"2024-06-01\",\n    \"parsed_year_month_day\": \"2024-06-03\",\n    \"parsed_year_month_day_hour\": \"2024-06-03 04:38:00\",\n    \"parsed_week\": 23,\n    \"parsed_wday\": 2,\n    \"parsed_wday_label\": \"Monday\"\n  },\n  {\n    \"dateHourMinute\": \"202406030439\",\n    \"activeUsers\": 1,\n    \"parsed_year\": \"2024\",\n    \"parsed_month\": \"06\",\n    \"parsed_day\": \"03\",\n    \"parsed_hour\": \"04\",\n    \"parsed_minute\": \"39\",\n    \"parsed_year_month\": \"2024-06-01\",\n    \"parsed_year_month_day\": \"2024-06-03\",\n    \"parsed_year_month_day_hour\": \"2024-06-03 04:39:00\",\n    \"parsed_week\": 23,\n    \"parsed_wday\": 2,\n    \"parsed_wday_label\": \"Monday\"\n  },\n  {\n    \"dateHourMinute\": \"202406030452\",\n    \"activeUsers\": 1,\n    \"parsed_year\": \"2024\",\n    \"parsed_month\": \"06\",\n    \"parsed_day\": \"03\",\n    \"parsed_hour\": \"04\",\n    \"parsed_minute\": \"52\",\n    \"parsed_year_month\": \"2024-06-01\",\n    \"parsed_year_month_day\": \"2024-06-03\",\n    \"parsed_year_month_day_hour\": \"2024-06-03 04:52:00\",\n    \"parsed_week\": 23,\n    \"parsed_wday\": 2,\n    \"parsed_wday_label\": \"Monday\"\n  },\n  {\n    \"dateHourMinute\": \"202406030454\",\n    \"activeUsers\": 1,\n    \"parsed_year\": \"2024\",\n    \"parsed_month\": \"06\",\n    \"parsed_day\": \"03\",\n    \"parsed_hour\": \"04\",\n    \"parsed_minute\": \"54\",\n    \"parsed_year_month\": \"2024-06-01\",\n    \"parsed_year_month_day\": \"2024-06-03\",\n    \"parsed_year_month_day_hour\": \"2024-06-03 04:54:00\",\n    \"parsed_week\": 23,\n    \"parsed_wday\": 2,\n    \"parsed_wday_label\": \"Monday\"\n  },\n  {\n    \"dateHourMinute\": \"202406030522\",\n    \"activeUsers\": 1,\n    \"parsed_year\": \"2024\",\n    \"parsed_month\": \"06\",\n    \"parsed_day\": \"03\",\n    \"parsed_hour\": \"05\",\n    \"parsed_minute\": \"22\",\n    \"parsed_year_month\": \"2024-06-01\",\n    \"parsed_year_month_day\": \"2024-06-03\",\n    \"parsed_year_month_day_hour\": \"2024-06-03 05:22:00\",\n    \"parsed_week\": 23,\n    \"parsed_wday\": 2,\n    \"parsed_wday_label\": \"Monday\"\n  },\n  {\n    \"dateHourMinute\": \"202406030952\",\n    \"activeUsers\": 1,\n    \"parsed_year\": \"2024\",\n    \"parsed_month\": \"06\",\n    \"parsed_day\": \"03\",\n    \"parsed_hour\": \"09\",\n    \"parsed_minute\": \"52\",\n    \"parsed_year_month\": \"2024-06-01\",\n    \"parsed_year_month_day\": \"2024-06-03\",\n    \"parsed_year_month_day_hour\": \"2024-06-03 09:52:00\",\n    \"parsed_week\": 23,\n    \"parsed_wday\": 2,\n    \"parsed_wday_label\": \"Monday\"\n  },\n  {\n    \"dateHourMinute\": \"202406031020\",\n    \"activeUsers\": 1,\n    \"parsed_year\": \"2024\",\n    \"parsed_month\": \"06\",\n    \"parsed_day\": \"03\",\n    \"parsed_hour\": \"10\",\n    \"parsed_minute\": \"20\",\n    \"parsed_year_month\": \"2024-06-01\",\n    \"parsed_year_month_day\": \"2024-06-03\",\n    \"parsed_year_month_day_hour\": \"2024-06-03 10:20:00\",\n    \"parsed_week\": 23,\n    \"parsed_wday\": 2,\n    \"parsed_wday_label\": \"Monday\"\n  },\n  {\n    \"dateHourMinute\": \"202406031022\",\n    \"activeUsers\": 1,\n    \"parsed_year\": \"2024\",\n    \"parsed_month\": \"06\",\n    \"parsed_day\": \"03\",\n    \"parsed_hour\": \"10\",\n    \"parsed_minute\": \"22\",\n    \"parsed_year_month\": \"2024-06-01\",\n    \"parsed_year_month_day\": \"2024-06-03\",\n    \"parsed_year_month_day_hour\": \"2024-06-03 10:22:00\",\n    \"parsed_week\": 23,\n    \"parsed_wday\": 2,\n    \"parsed_wday_label\": \"Monday\"\n  },\n  {\n    \"dateHourMinute\": \"202406031027\",\n    \"activeUsers\": 1,\n    \"parsed_year\": \"2024\",\n    \"parsed_month\": \"06\",\n    \"parsed_day\": \"03\",\n    \"parsed_hour\": \"10\",\n    \"parsed_minute\": \"27\",\n    \"parsed_year_month\": \"2024-06-01\",\n    \"parsed_year_month_day\": \"2024-06-03\",\n    \"parsed_year_month_day_hour\": \"2024-06-03 10:27:00\",\n    \"parsed_week\": 23,\n    \"parsed_wday\": 2,\n    \"parsed_wday_label\": \"Monday\"\n  },\n  {\n    \"dateHourMinute\": \"202406031029\",\n    \"activeUsers\": 1,\n    \"parsed_year\": \"2024\",\n    \"parsed_month\": \"06\",\n    \"parsed_day\": \"03\",\n    \"parsed_hour\": \"10\",\n    \"parsed_minute\": \"29\",\n    \"parsed_year_month\": \"2024-06-01\",\n    \"parsed_year_month_day\": \"2024-06-03\",\n    \"parsed_year_month_day_hour\": \"2024-06-03 10:29:00\",\n    \"parsed_week\": 23,\n    \"parsed_wday\": 2,\n    \"parsed_wday_label\": \"Monday\"\n  },\n  {\n    \"dateHourMinute\": \"202406031041\",\n    \"activeUsers\": 1,\n    \"parsed_year\": \"2024\",\n    \"parsed_month\": \"06\",\n    \"parsed_day\": \"03\",\n    \"parsed_hour\": \"10\",\n    \"parsed_minute\": \"41\",\n    \"parsed_year_month\": \"2024-06-01\",\n    \"parsed_year_month_day\": \"2024-06-03\",\n    \"parsed_year_month_day_hour\": \"2024-06-03 10:41:00\",\n    \"parsed_week\": 23,\n    \"parsed_wday\": 2,\n    \"parsed_wday_label\": \"Monday\"\n  },\n  {\n    \"dateHourMinute\": \"202406031047\",\n    \"activeUsers\": 1,\n    \"parsed_year\": \"2024\",\n    \"parsed_month\": \"06\",\n    \"parsed_day\": \"03\",\n    \"parsed_hour\": \"10\",\n    \"parsed_minute\": \"47\",\n    \"parsed_year_month\": \"2024-06-01\",\n    \"parsed_year_month_day\": \"2024-06-03\",\n    \"parsed_year_month_day_hour\": \"2024-06-03 10:47:00\",\n    \"parsed_week\": 23,\n    \"parsed_wday\": 2,\n    \"parsed_wday_label\": \"Monday\"\n  },\n  {\n    \"dateHourMinute\": \"202406031048\",\n    \"activeUsers\": 1,\n    \"parsed_year\": \"2024\",\n    \"parsed_month\": \"06\",\n    \"parsed_day\": \"03\",\n    \"parsed_hour\": \"10\",\n    \"parsed_minute\": \"48\",\n    \"parsed_year_month\": \"2024-06-01\",\n    \"parsed_year_month_day\": \"2024-06-03\",\n    \"parsed_year_month_day_hour\": \"2024-06-03 10:48:00\",\n    \"parsed_week\": 23,\n    \"parsed_wday\": 2,\n    \"parsed_wday_label\": \"Monday\"\n  },\n  {\n    \"dateHourMinute\": \"202406031049\",\n    \"activeUsers\": 2,\n    \"parsed_year\": \"2024\",\n    \"parsed_month\": \"06\",\n    \"parsed_day\": \"03\",\n    \"parsed_hour\": \"10\",\n    \"parsed_minute\": \"49\",\n    \"parsed_year_month\": \"2024-06-01\",\n    \"parsed_year_month_day\": \"2024-06-03\",\n    \"parsed_year_month_day_hour\": \"2024-06-03 10:49:00\",\n    \"parsed_week\": 23,\n    \"parsed_wday\": 2,\n    \"parsed_wday_label\": \"Monday\"\n  },\n  {\n    \"dateHourMinute\": \"202406031051\",\n    \"activeUsers\": 1,\n    \"parsed_year\": \"2024\",\n    \"parsed_month\": \"06\",\n    \"parsed_day\": \"03\",\n    \"parsed_hour\": \"10\",\n    \"parsed_minute\": \"51\",\n    \"parsed_year_month\": \"2024-06-01\",\n    \"parsed_year_month_day\": \"2024-06-03\",\n    \"parsed_year_month_day_hour\": \"2024-06-03 10:51:00\",\n    \"parsed_week\": 23,\n    \"parsed_wday\": 2,\n    \"parsed_wday_label\": \"Monday\"\n  },\n  {\n    \"dateHourMinute\": \"202406031103\",\n    \"activeUsers\": 1,\n    \"parsed_year\": \"2024\",\n    \"parsed_month\": \"06\",\n    \"parsed_day\": \"03\",\n    \"parsed_hour\": \"11\",\n    \"parsed_minute\": \"03\",\n    \"parsed_year_month\": \"2024-06-01\",\n    \"parsed_year_month_day\": \"2024-06-03\",\n    \"parsed_year_month_day_hour\": \"2024-06-03 11:03:00\",\n    \"parsed_week\": 23,\n    \"parsed_wday\": 2,\n    \"parsed_wday_label\": \"Monday\"\n  },\n  {\n    \"dateHourMinute\": \"202406031104\",\n    \"activeUsers\": 1,\n    \"parsed_year\": \"2024\",\n    \"parsed_month\": \"06\",\n    \"parsed_day\": \"03\",\n    \"parsed_hour\": \"11\",\n    \"parsed_minute\": \"04\",\n    \"parsed_year_month\": \"2024-06-01\",\n    \"parsed_year_month_day\": \"2024-06-03\",\n    \"parsed_year_month_day_hour\": \"2024-06-03 11:04:00\",\n    \"parsed_week\": 23,\n    \"parsed_wday\": 2,\n    \"parsed_wday_label\": \"Monday\"\n  },\n  {\n    \"dateHourMinute\": \"202406031105\",\n    \"activeUsers\": 1,\n    \"parsed_year\": \"2024\",\n    \"parsed_month\": \"06\",\n    \"parsed_day\": \"03\",\n    \"parsed_hour\": \"11\",\n    \"parsed_minute\": \"05\",\n    \"parsed_year_month\": \"2024-06-01\",\n    \"parsed_year_month_day\": \"2024-06-03\",\n    \"parsed_year_month_day_hour\": \"2024-06-03 11:05:00\",\n    \"parsed_week\": 23,\n    \"parsed_wday\": 2,\n    \"parsed_wday_label\": \"Monday\"\n  },\n  {\n    \"dateHourMinute\": \"202406031106\",\n    \"activeUsers\": 1,\n    \"parsed_year\": \"2024\",\n    \"parsed_month\": \"06\",\n    \"parsed_day\": \"03\",\n    \"parsed_hour\": \"11\",\n    \"parsed_minute\": \"06\",\n    \"parsed_year_month\": \"2024-06-01\",\n    \"parsed_year_month_day\": \"2024-06-03\",\n    \"parsed_year_month_day_hour\": \"2024-06-03 11:06:00\",\n    \"parsed_week\": 23,\n    \"parsed_wday\": 2,\n    \"parsed_wday_label\": \"Monday\"\n  },\n  {\n    \"dateHourMinute\": \"202406031235\",\n    \"activeUsers\": 1,\n    \"parsed_year\": \"2024\",\n    \"parsed_month\": \"06\",\n    \"parsed_day\": \"03\",\n    \"parsed_hour\": \"12\",\n    \"parsed_minute\": \"35\",\n    \"parsed_year_month\": \"2024-06-01\",\n    \"parsed_year_month_day\": \"2024-06-03\",\n    \"parsed_year_month_day_hour\": \"2024-06-03 12:35:00\",\n    \"parsed_week\": 23,\n    \"parsed_wday\": 2,\n    \"parsed_wday_label\": \"Monday\"\n  },\n  {\n    \"dateHourMinute\": \"202406031319\",\n    \"activeUsers\": 1,\n    \"parsed_year\": \"2024\",\n    \"parsed_month\": \"06\",\n    \"parsed_day\": \"03\",\n    \"parsed_hour\": \"13\",\n    \"parsed_minute\": \"19\",\n    \"parsed_year_month\": \"2024-06-01\",\n    \"parsed_year_month_day\": \"2024-06-03\",\n    \"parsed_year_month_day_hour\": \"2024-06-03 13:19:00\",\n    \"parsed_week\": 23,\n    \"parsed_wday\": 2,\n    \"parsed_wday_label\": \"Monday\"\n  },\n  {\n    \"dateHourMinute\": \"202406031325\",\n    \"activeUsers\": 1,\n    \"parsed_year\": \"2024\",\n    \"parsed_month\": \"06\",\n    \"parsed_day\": \"03\",\n    \"parsed_hour\": \"13\",\n    \"parsed_minute\": \"25\",\n    \"parsed_year_month\": \"2024-06-01\",\n    \"parsed_year_month_day\": \"2024-06-03\",\n    \"parsed_year_month_day_hour\": \"2024-06-03 13:25:00\",\n    \"parsed_week\": 23,\n    \"parsed_wday\": 2,\n    \"parsed_wday_label\": \"Monday\"\n  },\n  {\n    \"dateHourMinute\": \"202406031332\",\n    \"activeUsers\": 1,\n    \"parsed_year\": \"2024\",\n    \"parsed_month\": \"06\",\n    \"parsed_day\": \"03\",\n    \"parsed_hour\": \"13\",\n    \"parsed_minute\": \"32\",\n    \"parsed_year_month\": \"2024-06-01\",\n    \"parsed_year_month_day\": \"2024-06-03\",\n    \"parsed_year_month_day_hour\": \"2024-06-03 13:32:00\",\n    \"parsed_week\": 23,\n    \"parsed_wday\": 2,\n    \"parsed_wday_label\": \"Monday\"\n  },\n  {\n    \"dateHourMinute\": \"202406031420\",\n    \"activeUsers\": 1,\n    \"parsed_year\": \"2024\",\n    \"parsed_month\": \"06\",\n    \"parsed_day\": \"03\",\n    \"parsed_hour\": \"14\",\n    \"parsed_minute\": \"20\",\n    \"parsed_year_month\": \"2024-06-01\",\n    \"parsed_year_month_day\": \"2024-06-03\",\n    \"parsed_year_month_day_hour\": \"2024-06-03 14:20:00\",\n    \"parsed_week\": 23,\n    \"parsed_wday\": 2,\n    \"parsed_wday_label\": \"Monday\"\n  },\n  {\n    \"dateHourMinute\": \"202406031421\",\n    \"activeUsers\": 1,\n    \"parsed_year\": \"2024\",\n    \"parsed_month\": \"06\",\n    \"parsed_day\": \"03\",\n    \"parsed_hour\": \"14\",\n    \"parsed_minute\": \"21\",\n    \"parsed_year_month\": \"2024-06-01\",\n    \"parsed_year_month_day\": \"2024-06-03\",\n    \"parsed_year_month_day_hour\": \"2024-06-03 14:21:00\",\n    \"parsed_week\": 23,\n    \"parsed_wday\": 2,\n    \"parsed_wday_label\": \"Monday\"\n  },\n  {\n    \"dateHourMinute\": \"202406031440\",\n    \"activeUsers\": 1,\n    \"parsed_year\": \"2024\",\n    \"parsed_month\": \"06\",\n    \"parsed_day\": \"03\",\n    \"parsed_hour\": \"14\",\n    \"parsed_minute\": \"40\",\n    \"parsed_year_month\": \"2024-06-01\",\n    \"parsed_year_month_day\": \"2024-06-03\",\n    \"parsed_year_month_day_hour\": \"2024-06-03 14:40:00\",\n    \"parsed_week\": 23,\n    \"parsed_wday\": 2,\n    \"parsed_wday_label\": \"Monday\"\n  },\n  {\n    \"dateHourMinute\": \"202406031442\",\n    \"activeUsers\": 1,\n    \"parsed_year\": \"2024\",\n    \"parsed_month\": \"06\",\n    \"parsed_day\": \"03\",\n    \"parsed_hour\": \"14\",\n    \"parsed_minute\": \"42\",\n    \"parsed_year_month\": \"2024-06-01\",\n    \"parsed_year_month_day\": \"2024-06-03\",\n    \"parsed_year_month_day_hour\": \"2024-06-03 14:42:00\",\n    \"parsed_week\": 23,\n    \"parsed_wday\": 2,\n    \"parsed_wday_label\": \"Monday\"\n  },\n  {\n    \"dateHourMinute\": \"202406031449\",\n    \"activeUsers\": 1,\n    \"parsed_year\": \"2024\",\n    \"parsed_month\": \"06\",\n    \"parsed_day\": \"03\",\n    \"parsed_hour\": \"14\",\n    \"parsed_minute\": \"49\",\n    \"parsed_year_month\": \"2024-06-01\",\n    \"parsed_year_month_day\": \"2024-06-03\",\n    \"parsed_year_month_day_hour\": \"2024-06-03 14:49:00\",\n    \"parsed_week\": 23,\n    \"parsed_wday\": 2,\n    \"parsed_wday_label\": \"Monday\"\n  },\n  {\n    \"dateHourMinute\": \"202406031450\",\n    \"activeUsers\": 1,\n    \"parsed_year\": \"2024\",\n    \"parsed_month\": \"06\",\n    \"parsed_day\": \"03\",\n    \"parsed_hour\": \"14\",\n    \"parsed_minute\": \"50\",\n    \"parsed_year_month\": \"2024-06-01\",\n    \"parsed_year_month_day\": \"2024-06-03\",\n    \"parsed_year_month_day_hour\": \"2024-06-03 14:50:00\",\n    \"parsed_week\": 23,\n    \"parsed_wday\": 2,\n    \"parsed_wday_label\": \"Monday\"\n  },\n  {\n    \"dateHourMinute\": \"202406031514\",\n    \"activeUsers\": 1,\n    \"parsed_year\": \"2024\",\n    \"parsed_month\": \"06\",\n    \"parsed_day\": \"03\",\n    \"parsed_hour\": \"15\",\n    \"parsed_minute\": \"14\",\n    \"parsed_year_month\": \"2024-06-01\",\n    \"parsed_year_month_day\": \"2024-06-03\",\n    \"parsed_year_month_day_hour\": \"2024-06-03 15:14:00\",\n    \"parsed_week\": 23,\n    \"parsed_wday\": 2,\n    \"parsed_wday_label\": \"Monday\"\n  },\n  {\n    \"dateHourMinute\": \"202406031545\",\n    \"activeUsers\": 1,\n    \"parsed_year\": \"2024\",\n    \"parsed_month\": \"06\",\n    \"parsed_day\": \"03\",\n    \"parsed_hour\": \"15\",\n    \"parsed_minute\": \"45\",\n    \"parsed_year_month\": \"2024-06-01\",\n    \"parsed_year_month_day\": \"2024-06-03\",\n    \"parsed_year_month_day_hour\": \"2024-06-03 15:45:00\",\n    \"parsed_week\": 23,\n    \"parsed_wday\": 2,\n    \"parsed_wday_label\": \"Monday\"\n  },\n  {\n    \"dateHourMinute\": \"202406031548\",\n    \"activeUsers\": 1,\n    \"parsed_year\": \"2024\",\n    \"parsed_month\": \"06\",\n    \"parsed_day\": \"03\",\n    \"parsed_hour\": \"15\",\n    \"parsed_minute\": \"48\",\n    \"parsed_year_month\": \"2024-06-01\",\n    \"parsed_year_month_day\": \"2024-06-03\",\n    \"parsed_year_month_day_hour\": \"2024-06-03 15:48:00\",\n    \"parsed_week\": 23,\n    \"parsed_wday\": 2,\n    \"parsed_wday_label\": \"Monday\"\n  },\n  {\n    \"dateHourMinute\": \"202406031605\",\n    \"activeUsers\": 1,\n    \"parsed_year\": \"2024\",\n    \"parsed_month\": \"06\",\n    \"parsed_day\": \"03\",\n    \"parsed_hour\": \"16\",\n    \"parsed_minute\": \"05\",\n    \"parsed_year_month\": \"2024-06-01\",\n    \"parsed_year_month_day\": \"2024-06-03\",\n    \"parsed_year_month_day_hour\": \"2024-06-03 16:05:00\",\n    \"parsed_week\": 23,\n    \"parsed_wday\": 2,\n    \"parsed_wday_label\": \"Monday\"\n  },\n  {\n    \"dateHourMinute\": \"202406031637\",\n    \"activeUsers\": 1,\n    \"parsed_year\": \"2024\",\n    \"parsed_month\": \"06\",\n    \"parsed_day\": \"03\",\n    \"parsed_hour\": \"16\",\n    \"parsed_minute\": \"37\",\n    \"parsed_year_month\": \"2024-06-01\",\n    \"parsed_year_month_day\": \"2024-06-03\",\n    \"parsed_year_month_day_hour\": \"2024-06-03 16:37:00\",\n    \"parsed_week\": 23,\n    \"parsed_wday\": 2,\n    \"parsed_wday_label\": \"Monday\"\n  },\n  {\n    \"dateHourMinute\": \"202406031638\",\n    \"activeUsers\": 1,\n    \"parsed_year\": \"2024\",\n    \"parsed_month\": \"06\",\n    \"parsed_day\": \"03\",\n    \"parsed_hour\": \"16\",\n    \"parsed_minute\": \"38\",\n    \"parsed_year_month\": \"2024-06-01\",\n    \"parsed_year_month_day\": \"2024-06-03\",\n    \"parsed_year_month_day_hour\": \"2024-06-03 16:38:00\",\n    \"parsed_week\": 23,\n    \"parsed_wday\": 2,\n    \"parsed_wday_label\": \"Monday\"\n  },\n  {\n    \"dateHourMinute\": \"202406031702\",\n    \"activeUsers\": 1,\n    \"parsed_year\": \"2024\",\n    \"parsed_month\": \"06\",\n    \"parsed_day\": \"03\",\n    \"parsed_hour\": \"17\",\n    \"parsed_minute\": \"02\",\n    \"parsed_year_month\": \"2024-06-01\",\n    \"parsed_year_month_day\": \"2024-06-03\",\n    \"parsed_year_month_day_hour\": \"2024-06-03 17:02:00\",\n    \"parsed_week\": 23,\n    \"parsed_wday\": 2,\n    \"parsed_wday_label\": \"Monday\"\n  },\n  {\n    \"dateHourMinute\": \"202406031703\",\n    \"activeUsers\": 1,\n    \"parsed_year\": \"2024\",\n    \"parsed_month\": \"06\",\n    \"parsed_day\": \"03\",\n    \"parsed_hour\": \"17\",\n    \"parsed_minute\": \"03\",\n    \"parsed_year_month\": \"2024-06-01\",\n    \"parsed_year_month_day\": \"2024-06-03\",\n    \"parsed_year_month_day_hour\": \"2024-06-03 17:03:00\",\n    \"parsed_week\": 23,\n    \"parsed_wday\": 2,\n    \"parsed_wday_label\": \"Monday\"\n  },\n  {\n    \"dateHourMinute\": \"202406031704\",\n    \"activeUsers\": 1,\n    \"parsed_year\": \"2024\",\n    \"parsed_month\": \"06\",\n    \"parsed_day\": \"03\",\n    \"parsed_hour\": \"17\",\n    \"parsed_minute\": \"04\",\n    \"parsed_year_month\": \"2024-06-01\",\n    \"parsed_year_month_day\": \"2024-06-03\",\n    \"parsed_year_month_day_hour\": \"2024-06-03 17:04:00\",\n    \"parsed_week\": 23,\n    \"parsed_wday\": 2,\n    \"parsed_wday_label\": \"Monday\"\n  },\n  {\n    \"dateHourMinute\": \"202406031738\",\n    \"activeUsers\": 1,\n    \"parsed_year\": \"2024\",\n    \"parsed_month\": \"06\",\n    \"parsed_day\": \"03\",\n    \"parsed_hour\": \"17\",\n    \"parsed_minute\": \"38\",\n    \"parsed_year_month\": \"2024-06-01\",\n    \"parsed_year_month_day\": \"2024-06-03\",\n    \"parsed_year_month_day_hour\": \"2024-06-03 17:38:00\",\n    \"parsed_week\": 23,\n    \"parsed_wday\": 2,\n    \"parsed_wday_label\": \"Monday\"\n  },\n  {\n    \"dateHourMinute\": \"202406031739\",\n    \"activeUsers\": 1,\n    \"parsed_year\": \"2024\",\n    \"parsed_month\": \"06\",\n    \"parsed_day\": \"03\",\n    \"parsed_hour\": \"17\",\n    \"parsed_minute\": \"39\",\n    \"parsed_year_month\": \"2024-06-01\",\n    \"parsed_year_month_day\": \"2024-06-03\",\n    \"parsed_year_month_day_hour\": \"2024-06-03 17:39:00\",\n    \"parsed_week\": 23,\n    \"parsed_wday\": 2,\n    \"parsed_wday_label\": \"Monday\"\n  },\n  {\n    \"dateHourMinute\": \"202406031759\",\n    \"activeUsers\": 1,\n    \"parsed_year\": \"2024\",\n    \"parsed_month\": \"06\",\n    \"parsed_day\": \"03\",\n    \"parsed_hour\": \"17\",\n    \"parsed_minute\": \"59\",\n    \"parsed_year_month\": \"2024-06-01\",\n    \"parsed_year_month_day\": \"2024-06-03\",\n    \"parsed_year_month_day_hour\": \"2024-06-03 17:59:00\",\n    \"parsed_week\": 23,\n    \"parsed_wday\": 2,\n    \"parsed_wday_label\": \"Monday\"\n  },\n  {\n    \"dateHourMinute\": \"202406031808\",\n    \"activeUsers\": 1,\n    \"parsed_year\": \"2024\",\n    \"parsed_month\": \"06\",\n    \"parsed_day\": \"03\",\n    \"parsed_hour\": \"18\",\n    \"parsed_minute\": \"08\",\n    \"parsed_year_month\": \"2024-06-01\",\n    \"parsed_year_month_day\": \"2024-06-03\",\n    \"parsed_year_month_day_hour\": \"2024-06-03 18:08:00\",\n    \"parsed_week\": 23,\n    \"parsed_wday\": 2,\n    \"parsed_wday_label\": \"Monday\"\n  },\n  {\n    \"dateHourMinute\": \"202406031809\",\n    \"activeUsers\": 1,\n    \"parsed_year\": \"2024\",\n    \"parsed_month\": \"06\",\n    \"parsed_day\": \"03\",\n    \"parsed_hour\": \"18\",\n    \"parsed_minute\": \"09\",\n    \"parsed_year_month\": \"2024-06-01\",\n    \"parsed_year_month_day\": \"2024-06-03\",\n    \"parsed_year_month_day_hour\": \"2024-06-03 18:09:00\",\n    \"parsed_week\": 23,\n    \"parsed_wday\": 2,\n    \"parsed_wday_label\": \"Monday\"\n  },\n  {\n    \"dateHourMinute\": \"202406031949\",\n    \"activeUsers\": 1,\n    \"parsed_year\": \"2024\",\n    \"parsed_month\": \"06\",\n    \"parsed_day\": \"03\",\n    \"parsed_hour\": \"19\",\n    \"parsed_minute\": \"49\",\n    \"parsed_year_month\": \"2024-06-01\",\n    \"parsed_year_month_day\": \"2024-06-03\",\n    \"parsed_year_month_day_hour\": \"2024-06-03 19:49:00\",\n    \"parsed_week\": 23,\n    \"parsed_wday\": 2,\n    \"parsed_wday_label\": \"Monday\"\n  },\n  {\n    \"dateHourMinute\": \"202406032004\",\n    \"activeUsers\": 1,\n    \"parsed_year\": \"2024\",\n    \"parsed_month\": \"06\",\n    \"parsed_day\": \"03\",\n    \"parsed_hour\": \"20\",\n    \"parsed_minute\": \"04\",\n    \"parsed_year_month\": \"2024-06-01\",\n    \"parsed_year_month_day\": \"2024-06-03\",\n    \"parsed_year_month_day_hour\": \"2024-06-03 20:04:00\",\n    \"parsed_week\": 23,\n    \"parsed_wday\": 2,\n    \"parsed_wday_label\": \"Monday\"\n  },\n  {\n    \"dateHourMinute\": \"202406032005\",\n    \"activeUsers\": 1,\n    \"parsed_year\": \"2024\",\n    \"parsed_month\": \"06\",\n    \"parsed_day\": \"03\",\n    \"parsed_hour\": \"20\",\n    \"parsed_minute\": \"05\",\n    \"parsed_year_month\": \"2024-06-01\",\n    \"parsed_year_month_day\": \"2024-06-03\",\n    \"parsed_year_month_day_hour\": \"2024-06-03 20:05:00\",\n    \"parsed_week\": 23,\n    \"parsed_wday\": 2,\n    \"parsed_wday_label\": \"Monday\"\n  },\n  {\n    \"dateHourMinute\": \"202406032050\",\n    \"activeUsers\": 2,\n    \"parsed_year\": \"2024\",\n    \"parsed_month\": \"06\",\n    \"parsed_day\": \"03\",\n    \"parsed_hour\": \"20\",\n    \"parsed_minute\": \"50\",\n    \"parsed_year_month\": \"2024-06-01\",\n    \"parsed_year_month_day\": \"2024-06-03\",\n    \"parsed_year_month_day_hour\": \"2024-06-03 20:50:00\",\n    \"parsed_week\": 23,\n    \"parsed_wday\": 2,\n    \"parsed_wday_label\": \"Monday\"\n  },\n  {\n    \"dateHourMinute\": \"202406032107\",\n    \"activeUsers\": 1,\n    \"parsed_year\": \"2024\",\n    \"parsed_month\": \"06\",\n    \"parsed_day\": \"03\",\n    \"parsed_hour\": \"21\",\n    \"parsed_minute\": \"07\",\n    \"parsed_year_month\": \"2024-06-01\",\n    \"parsed_year_month_day\": \"2024-06-03\",\n    \"parsed_year_month_day_hour\": \"2024-06-03 21:07:00\",\n    \"parsed_week\": 23,\n    \"parsed_wday\": 2,\n    \"parsed_wday_label\": \"Monday\"\n  },\n  {\n    \"dateHourMinute\": \"202406032227\",\n    \"activeUsers\": 1,\n    \"parsed_year\": \"2024\",\n    \"parsed_month\": \"06\",\n    \"parsed_day\": \"03\",\n    \"parsed_hour\": \"22\",\n    \"parsed_minute\": \"27\",\n    \"parsed_year_month\": \"2024-06-01\",\n    \"parsed_year_month_day\": \"2024-06-03\",\n    \"parsed_year_month_day_hour\": \"2024-06-03 22:27:00\",\n    \"parsed_week\": 23,\n    \"parsed_wday\": 2,\n    \"parsed_wday_label\": \"Monday\"\n  },\n  {\n    \"dateHourMinute\": \"202406032232\",\n    \"activeUsers\": 1,\n    \"parsed_year\": \"2024\",\n    \"parsed_month\": \"06\",\n    \"parsed_day\": \"03\",\n    \"parsed_hour\": \"22\",\n    \"parsed_minute\": \"32\",\n    \"parsed_year_month\": \"2024-06-01\",\n    \"parsed_year_month_day\": \"2024-06-03\",\n    \"parsed_year_month_day_hour\": \"2024-06-03 22:32:00\",\n    \"parsed_week\": 23,\n    \"parsed_wday\": 2,\n    \"parsed_wday_label\": \"Monday\"\n  },\n  {\n    \"dateHourMinute\": \"202406032233\",\n    \"activeUsers\": 1,\n    \"parsed_year\": \"2024\",\n    \"parsed_month\": \"06\",\n    \"parsed_day\": \"03\",\n    \"parsed_hour\": \"22\",\n    \"parsed_minute\": \"33\",\n    \"parsed_year_month\": \"2024-06-01\",\n    \"parsed_year_month_day\": \"2024-06-03\",\n    \"parsed_year_month_day_hour\": \"2024-06-03 22:33:00\",\n    \"parsed_week\": 23,\n    \"parsed_wday\": 2,\n    \"parsed_wday_label\": \"Monday\"\n  }\n]"]
