["[\n  {\n    \"dateHourMinute\": \"202510200409\",\n    \"activeUsers\": 1,\n    \"parsed_year\": \"2025\",\n    \"parsed_month\": \"10\",\n    \"parsed_day\": \"20\",\n    \"parsed_hour\": \"04\",\n    \"parsed_minute\": \"09\",\n    \"parsed_year_month\": \"2025-10-01\",\n    \"parsed_year_month_day\": \"2025-10-20\",\n    \"parsed_year_month_day_hour\": \"2025-10-20 04:09:00\",\n    \"parsed_week\": 42,\n    \"parsed_wday\": 2,\n    \"parsed_wday_label\": \"Monday\"\n  },\n  {\n    \"dateHourMinute\": \"202510200417\",\n    \"activeUsers\": 1,\n    \"parsed_year\": \"2025\",\n    \"parsed_month\": \"10\",\n    \"parsed_day\": \"20\",\n    \"parsed_hour\": \"04\",\n    \"parsed_minute\": \"17\",\n    \"parsed_year_month\": \"2025-10-01\",\n    \"parsed_year_month_day\": \"2025-10-20\",\n    \"parsed_year_month_day_hour\": \"2025-10-20 04:17:00\",\n    \"parsed_week\": 42,\n    \"parsed_wday\": 2,\n    \"parsed_wday_label\": \"Monday\"\n  },\n  {\n    \"dateHourMinute\": \"202510200559\",\n    \"activeUsers\": 1,\n    \"parsed_year\": \"2025\",\n    \"parsed_month\": \"10\",\n    \"parsed_day\": \"20\",\n    \"parsed_hour\": \"05\",\n    \"parsed_minute\": \"59\",\n    \"parsed_year_month\": \"2025-10-01\",\n    \"parsed_year_month_day\": \"2025-10-20\",\n    \"parsed_year_month_day_hour\": \"2025-10-20 05:59:00\",\n    \"parsed_week\": 42,\n    \"parsed_wday\": 2,\n    \"parsed_wday_label\": \"Monday\"\n  },\n  {\n    \"dateHourMinute\": \"202510200856\",\n    \"activeUsers\": 1,\n    \"parsed_year\": \"2025\",\n    \"parsed_month\": \"10\",\n    \"parsed_day\": \"20\",\n    \"parsed_hour\": \"08\",\n    \"parsed_minute\": \"56\",\n    \"parsed_year_month\": \"2025-10-01\",\n    \"parsed_year_month_day\": \"2025-10-20\",\n    \"parsed_year_month_day_hour\": \"2025-10-20 08:56:00\",\n    \"parsed_week\": 42,\n    \"parsed_wday\": 2,\n    \"parsed_wday_label\": \"Monday\"\n  },\n  {\n    \"dateHourMinute\": \"202510200857\",\n    \"activeUsers\": 1,\n    \"parsed_year\": \"2025\",\n    \"parsed_month\": \"10\",\n    \"parsed_day\": \"20\",\n    \"parsed_hour\": \"08\",\n    \"parsed_minute\": \"57\",\n    \"parsed_year_month\": \"2025-10-01\",\n    \"parsed_year_month_day\": \"2025-10-20\",\n    \"parsed_year_month_day_hour\": \"2025-10-20 08:57:00\",\n    \"parsed_week\": 42,\n    \"parsed_wday\": 2,\n    \"parsed_wday_label\": \"Monday\"\n  },\n  {\n    \"dateHourMinute\": \"202510201023\",\n    \"activeUsers\": 1,\n    \"parsed_year\": \"2025\",\n    \"parsed_month\": \"10\",\n    \"parsed_day\": \"20\",\n    \"parsed_hour\": \"10\",\n    \"parsed_minute\": \"23\",\n    \"parsed_year_month\": \"2025-10-01\",\n    \"parsed_year_month_day\": \"2025-10-20\",\n    \"parsed_year_month_day_hour\": \"2025-10-20 10:23:00\",\n    \"parsed_week\": 42,\n    \"parsed_wday\": 2,\n    \"parsed_wday_label\": \"Monday\"\n  },\n  {\n    \"dateHourMinute\": \"202510201027\",\n    \"activeUsers\": 1,\n    \"parsed_year\": \"2025\",\n    \"parsed_month\": \"10\",\n    \"parsed_day\": \"20\",\n    \"parsed_hour\": \"10\",\n    \"parsed_minute\": \"27\",\n    \"parsed_year_month\": \"2025-10-01\",\n    \"parsed_year_month_day\": \"2025-10-20\",\n    \"parsed_year_month_day_hour\": \"2025-10-20 10:27:00\",\n    \"parsed_week\": 42,\n    \"parsed_wday\": 2,\n    \"parsed_wday_label\": \"Monday\"\n  },\n  {\n    \"dateHourMinute\": \"202510201028\",\n    \"activeUsers\": 1,\n    \"parsed_year\": \"2025\",\n    \"parsed_month\": \"10\",\n    \"parsed_day\": \"20\",\n    \"parsed_hour\": \"10\",\n    \"parsed_minute\": \"28\",\n    \"parsed_year_month\": \"2025-10-01\",\n    \"parsed_year_month_day\": \"2025-10-20\",\n    \"parsed_year_month_day_hour\": \"2025-10-20 10:28:00\",\n    \"parsed_week\": 42,\n    \"parsed_wday\": 2,\n    \"parsed_wday_label\": \"Monday\"\n  },\n  {\n    \"dateHourMinute\": \"202510201105\",\n    \"activeUsers\": 1,\n    \"parsed_year\": \"2025\",\n    \"parsed_month\": \"10\",\n    \"parsed_day\": \"20\",\n    \"parsed_hour\": \"11\",\n    \"parsed_minute\": \"05\",\n    \"parsed_year_month\": \"2025-10-01\",\n    \"parsed_year_month_day\": \"2025-10-20\",\n    \"parsed_year_month_day_hour\": \"2025-10-20 11:05:00\",\n    \"parsed_week\": 42,\n    \"parsed_wday\": 2,\n    \"parsed_wday_label\": \"Monday\"\n  },\n  {\n    \"dateHourMinute\": \"202510201227\",\n    \"activeUsers\": 1,\n    \"parsed_year\": \"2025\",\n    \"parsed_month\": \"10\",\n    \"parsed_day\": \"20\",\n    \"parsed_hour\": \"12\",\n    \"parsed_minute\": \"27\",\n    \"parsed_year_month\": \"2025-10-01\",\n    \"parsed_year_month_day\": \"2025-10-20\",\n    \"parsed_year_month_day_hour\": \"2025-10-20 12:27:00\",\n    \"parsed_week\": 42,\n    \"parsed_wday\": 2,\n    \"parsed_wday_label\": \"Monday\"\n  },\n  {\n    \"dateHourMinute\": \"202510201404\",\n    \"activeUsers\": 1,\n    \"parsed_year\": \"2025\",\n    \"parsed_month\": \"10\",\n    \"parsed_day\": \"20\",\n    \"parsed_hour\": \"14\",\n    \"parsed_minute\": \"04\",\n    \"parsed_year_month\": \"2025-10-01\",\n    \"parsed_year_month_day\": \"2025-10-20\",\n    \"parsed_year_month_day_hour\": \"2025-10-20 14:04:00\",\n    \"parsed_week\": 42,\n    \"parsed_wday\": 2,\n    \"parsed_wday_label\": \"Monday\"\n  },\n  {\n    \"dateHourMinute\": \"202510201452\",\n    \"activeUsers\": 1,\n    \"parsed_year\": \"2025\",\n    \"parsed_month\": \"10\",\n    \"parsed_day\": \"20\",\n    \"parsed_hour\": \"14\",\n    \"parsed_minute\": \"52\",\n    \"parsed_year_month\": \"2025-10-01\",\n    \"parsed_year_month_day\": \"2025-10-20\",\n    \"parsed_year_month_day_hour\": \"2025-10-20 14:52:00\",\n    \"parsed_week\": 42,\n    \"parsed_wday\": 2,\n    \"parsed_wday_label\": \"Monday\"\n  },\n  {\n    \"dateHourMinute\": \"202510201453\",\n    \"activeUsers\": 1,\n    \"parsed_year\": \"2025\",\n    \"parsed_month\": \"10\",\n    \"parsed_day\": \"20\",\n    \"parsed_hour\": \"14\",\n    \"parsed_minute\": \"53\",\n    \"parsed_year_month\": \"2025-10-01\",\n    \"parsed_year_month_day\": \"2025-10-20\",\n    \"parsed_year_month_day_hour\": \"2025-10-20 14:53:00\",\n    \"parsed_week\": 42,\n    \"parsed_wday\": 2,\n    \"parsed_wday_label\": \"Monday\"\n  },\n  {\n    \"dateHourMinute\": \"202510201502\",\n    \"activeUsers\": 1,\n    \"parsed_year\": \"2025\",\n    \"parsed_month\": \"10\",\n    \"parsed_day\": \"20\",\n    \"parsed_hour\": \"15\",\n    \"parsed_minute\": \"02\",\n    \"parsed_year_month\": \"2025-10-01\",\n    \"parsed_year_month_day\": \"2025-10-20\",\n    \"parsed_year_month_day_hour\": \"2025-10-20 15:02:00\",\n    \"parsed_week\": 42,\n    \"parsed_wday\": 2,\n    \"parsed_wday_label\": \"Monday\"\n  },\n  {\n    \"dateHourMinute\": \"202510201625\",\n    \"activeUsers\": 1,\n    \"parsed_year\": \"2025\",\n    \"parsed_month\": \"10\",\n    \"parsed_day\": \"20\",\n    \"parsed_hour\": \"16\",\n    \"parsed_minute\": \"25\",\n    \"parsed_year_month\": \"2025-10-01\",\n    \"parsed_year_month_day\": \"2025-10-20\",\n    \"parsed_year_month_day_hour\": \"2025-10-20 16:25:00\",\n    \"parsed_week\": 42,\n    \"parsed_wday\": 2,\n    \"parsed_wday_label\": \"Monday\"\n  },\n  {\n    \"dateHourMinute\": \"202510201704\",\n    \"activeUsers\": 1,\n    \"parsed_year\": \"2025\",\n    \"parsed_month\": \"10\",\n    \"parsed_day\": \"20\",\n    \"parsed_hour\": \"17\",\n    \"parsed_minute\": \"04\",\n    \"parsed_year_month\": \"2025-10-01\",\n    \"parsed_year_month_day\": \"2025-10-20\",\n    \"parsed_year_month_day_hour\": \"2025-10-20 17:04:00\",\n    \"parsed_week\": 42,\n    \"parsed_wday\": 2,\n    \"parsed_wday_label\": \"Monday\"\n  },\n  {\n    \"dateHourMinute\": \"202510201824\",\n    \"activeUsers\": 1,\n    \"parsed_year\": \"2025\",\n    \"parsed_month\": \"10\",\n    \"parsed_day\": \"20\",\n    \"parsed_hour\": \"18\",\n    \"parsed_minute\": \"24\",\n    \"parsed_year_month\": \"2025-10-01\",\n    \"parsed_year_month_day\": \"2025-10-20\",\n    \"parsed_year_month_day_hour\": \"2025-10-20 18:24:00\",\n    \"parsed_week\": 42,\n    \"parsed_wday\": 2,\n    \"parsed_wday_label\": \"Monday\"\n  },\n  {\n    \"dateHourMinute\": \"202510201900\",\n    \"activeUsers\": 1,\n    \"parsed_year\": \"2025\",\n    \"parsed_month\": \"10\",\n    \"parsed_day\": \"20\",\n    \"parsed_hour\": \"19\",\n    \"parsed_minute\": \"00\",\n    \"parsed_year_month\": \"2025-10-01\",\n    \"parsed_year_month_day\": \"2025-10-20\",\n    \"parsed_year_month_day_hour\": \"2025-10-20 19:00:00\",\n    \"parsed_week\": 42,\n    \"parsed_wday\": 2,\n    \"parsed_wday_label\": \"Monday\"\n  },\n  {\n    \"dateHourMinute\": \"202510202000\",\n    \"activeUsers\": 1,\n    \"parsed_year\": \"2025\",\n    \"parsed_month\": \"10\",\n    \"parsed_day\": \"20\",\n    \"parsed_hour\": \"20\",\n    \"parsed_minute\": \"00\",\n    \"parsed_year_month\": \"2025-10-01\",\n    \"parsed_year_month_day\": \"2025-10-20\",\n    \"parsed_year_month_day_hour\": \"2025-10-20 20:00:00\",\n    \"parsed_week\": 42,\n    \"parsed_wday\": 2,\n    \"parsed_wday_label\": \"Monday\"\n  },\n  {\n    \"dateHourMinute\": \"202510202223\",\n    \"activeUsers\": 1,\n    \"parsed_year\": \"2025\",\n    \"parsed_month\": \"10\",\n    \"parsed_day\": \"20\",\n    \"parsed_hour\": \"22\",\n    \"parsed_minute\": \"23\",\n    \"parsed_year_month\": \"2025-10-01\",\n    \"parsed_year_month_day\": \"2025-10-20\",\n    \"parsed_year_month_day_hour\": \"2025-10-20 22:23:00\",\n    \"parsed_week\": 42,\n    \"parsed_wday\": 2,\n    \"parsed_wday_label\": \"Monday\"\n  },\n  {\n    \"dateHourMinute\": \"202510202359\",\n    \"activeUsers\": 1,\n    \"parsed_year\": \"2025\",\n    \"parsed_month\": \"10\",\n    \"parsed_day\": \"20\",\n    \"parsed_hour\": \"23\",\n    \"parsed_minute\": \"59\",\n    \"parsed_year_month\": \"2025-10-01\",\n    \"parsed_year_month_day\": \"2025-10-20\",\n    \"parsed_year_month_day_hour\": \"2025-10-20 23:59:00\",\n    \"parsed_week\": 42,\n    \"parsed_wday\": 2,\n    \"parsed_wday_label\": \"Monday\"\n  }\n]"]
