[{"dateHourMinute":"202604280838","activeUsers":1,"parsed_year":"2026","parsed_month":"04","parsed_day":"28","parsed_hour":"08","parsed_minute":"38","parsed_year_month":"2026-04-01","parsed_year_month_day":"2026-04-28","parsed_year_month_day_hour":"2026-04-28 08:38:00","parsed_week":18,"parsed_wday":3,"parsed_wday_label":"Tuesday"},{"dateHourMinute":"202604281105","activeUsers":1,"parsed_year":"2026","parsed_month":"04","parsed_day":"28","parsed_hour":"11","parsed_minute":"05","parsed_year_month":"2026-04-01","parsed_year_month_day":"2026-04-28","parsed_year_month_day_hour":"2026-04-28 11:05:00","parsed_week":18,"parsed_wday":3,"parsed_wday_label":"Tuesday"},{"dateHourMinute":"202604281130","activeUsers":1,"parsed_year":"2026","parsed_month":"04","parsed_day":"28","parsed_hour":"11","parsed_minute":"30","parsed_year_month":"2026-04-01","parsed_year_month_day":"2026-04-28","parsed_year_month_day_hour":"2026-04-28 11:30:00","parsed_week":18,"parsed_wday":3,"parsed_wday_label":"Tuesday"},{"dateHourMinute":"202604281253","activeUsers":1,"parsed_year":"2026","parsed_month":"04","parsed_day":"28","parsed_hour":"12","parsed_minute":"53","parsed_year_month":"2026-04-01","parsed_year_month_day":"2026-04-28","parsed_year_month_day_hour":"2026-04-28 12:53:00","parsed_week":18,"parsed_wday":3,"parsed_wday_label":"Tuesday"},{"dateHourMinute":"202604281559","activeUsers":1,"parsed_year":"2026","parsed_month":"04","parsed_day":"28","parsed_hour":"15","parsed_minute":"59","parsed_year_month":"2026-04-01","parsed_year_month_day":"2026-04-28","parsed_year_month_day_hour":"2026-04-28 15:59:00","parsed_week":18,"parsed_wday":3,"parsed_wday_label":"Tuesday"},{"dateHourMinute":"202604281752","activeUsers":1,"parsed_year":"2026","parsed_month":"04","parsed_day":"28","parsed_hour":"17","parsed_minute":"52","parsed_year_month":"2026-04-01","parsed_year_month_day":"2026-04-28","parsed_year_month_day_hour":"2026-04-28 17:52:00","parsed_week":18,"parsed_wday":3,"parsed_wday_label":"Tuesday"},{"dateHourMinute":"202604281842","activeUsers":1,"parsed_year":"2026","parsed_month":"04","parsed_day":"28","parsed_hour":"18","parsed_minute":"42","parsed_year_month":"2026-04-01","parsed_year_month_day":"2026-04-28","parsed_year_month_day_hour":"2026-04-28 18:42:00","parsed_week":18,"parsed_wday":3,"parsed_wday_label":"Tuesday"},{"dateHourMinute":"202604281919","activeUsers":1,"parsed_year":"2026","parsed_month":"04","parsed_day":"28","parsed_hour":"19","parsed_minute":"19","parsed_year_month":"2026-04-01","parsed_year_month_day":"2026-04-28","parsed_year_month_day_hour":"2026-04-28 19:19:00","parsed_week":18,"parsed_wday":3,"parsed_wday_label":"Tuesday"}]
