["[\n  {\n    \"dateHourMinute\": \"202601171107\",\n    \"activeUsers\": 1,\n    \"parsed_year\": \"2026\",\n    \"parsed_month\": \"01\",\n    \"parsed_day\": \"17\",\n    \"parsed_hour\": \"11\",\n    \"parsed_minute\": \"07\",\n    \"parsed_year_month\": \"2026-01-01\",\n    \"parsed_year_month_day\": \"2026-01-17\",\n    \"parsed_year_month_day_hour\": \"2026-01-17 11:07:00\",\n    \"parsed_week\": 3,\n    \"parsed_wday\": 7,\n    \"parsed_wday_label\": \"Saturday\"\n  },\n  {\n    \"dateHourMinute\": \"202601171108\",\n    \"activeUsers\": 1,\n    \"parsed_year\": \"2026\",\n    \"parsed_month\": \"01\",\n    \"parsed_day\": \"17\",\n    \"parsed_hour\": \"11\",\n    \"parsed_minute\": \"08\",\n    \"parsed_year_month\": \"2026-01-01\",\n    \"parsed_year_month_day\": \"2026-01-17\",\n    \"parsed_year_month_day_hour\": \"2026-01-17 11:08:00\",\n    \"parsed_week\": 3,\n    \"parsed_wday\": 7,\n    \"parsed_wday_label\": \"Saturday\"\n  },\n  {\n    \"dateHourMinute\": \"202601171109\",\n    \"activeUsers\": 1,\n    \"parsed_year\": \"2026\",\n    \"parsed_month\": \"01\",\n    \"parsed_day\": \"17\",\n    \"parsed_hour\": \"11\",\n    \"parsed_minute\": \"09\",\n    \"parsed_year_month\": \"2026-01-01\",\n    \"parsed_year_month_day\": \"2026-01-17\",\n    \"parsed_year_month_day_hour\": \"2026-01-17 11:09:00\",\n    \"parsed_week\": 3,\n    \"parsed_wday\": 7,\n    \"parsed_wday_label\": \"Saturday\"\n  },\n  {\n    \"dateHourMinute\": \"202601171206\",\n    \"activeUsers\": 1,\n    \"parsed_year\": \"2026\",\n    \"parsed_month\": \"01\",\n    \"parsed_day\": \"17\",\n    \"parsed_hour\": \"12\",\n    \"parsed_minute\": \"06\",\n    \"parsed_year_month\": \"2026-01-01\",\n    \"parsed_year_month_day\": \"2026-01-17\",\n    \"parsed_year_month_day_hour\": \"2026-01-17 12:06:00\",\n    \"parsed_week\": 3,\n    \"parsed_wday\": 7,\n    \"parsed_wday_label\": \"Saturday\"\n  },\n  {\n    \"dateHourMinute\": \"202601171211\",\n    \"activeUsers\": 1,\n    \"parsed_year\": \"2026\",\n    \"parsed_month\": \"01\",\n    \"parsed_day\": \"17\",\n    \"parsed_hour\": \"12\",\n    \"parsed_minute\": \"11\",\n    \"parsed_year_month\": \"2026-01-01\",\n    \"parsed_year_month_day\": \"2026-01-17\",\n    \"parsed_year_month_day_hour\": \"2026-01-17 12:11:00\",\n    \"parsed_week\": 3,\n    \"parsed_wday\": 7,\n    \"parsed_wday_label\": \"Saturday\"\n  },\n  {\n    \"dateHourMinute\": \"202601171434\",\n    \"activeUsers\": 1,\n    \"parsed_year\": \"2026\",\n    \"parsed_month\": \"01\",\n    \"parsed_day\": \"17\",\n    \"parsed_hour\": \"14\",\n    \"parsed_minute\": \"34\",\n    \"parsed_year_month\": \"2026-01-01\",\n    \"parsed_year_month_day\": \"2026-01-17\",\n    \"parsed_year_month_day_hour\": \"2026-01-17 14:34:00\",\n    \"parsed_week\": 3,\n    \"parsed_wday\": 7,\n    \"parsed_wday_label\": \"Saturday\"\n  },\n  {\n    \"dateHourMinute\": \"202601171435\",\n    \"activeUsers\": 1,\n    \"parsed_year\": \"2026\",\n    \"parsed_month\": \"01\",\n    \"parsed_day\": \"17\",\n    \"parsed_hour\": \"14\",\n    \"parsed_minute\": \"35\",\n    \"parsed_year_month\": \"2026-01-01\",\n    \"parsed_year_month_day\": \"2026-01-17\",\n    \"parsed_year_month_day_hour\": \"2026-01-17 14:35:00\",\n    \"parsed_week\": 3,\n    \"parsed_wday\": 7,\n    \"parsed_wday_label\": \"Saturday\"\n  },\n  {\n    \"dateHourMinute\": \"202601171437\",\n    \"activeUsers\": 1,\n    \"parsed_year\": \"2026\",\n    \"parsed_month\": \"01\",\n    \"parsed_day\": \"17\",\n    \"parsed_hour\": \"14\",\n    \"parsed_minute\": \"37\",\n    \"parsed_year_month\": \"2026-01-01\",\n    \"parsed_year_month_day\": \"2026-01-17\",\n    \"parsed_year_month_day_hour\": \"2026-01-17 14:37:00\",\n    \"parsed_week\": 3,\n    \"parsed_wday\": 7,\n    \"parsed_wday_label\": \"Saturday\"\n  }\n]"]